[{"ANIO":2025,"MES":12,"DPTO_HECHO":"LAMBAYEQUE","PROV_HECHO":"CHICLAYO","DIST_HECHO":"CHICLAYO","ID_MODALIDAD":"01050101","MODALIDAD":"HURTO","xx":-6.75,"yy":-79.85,"CASOS":86},{"ANIO":2025,"MES":7,"DPTO_HECHO":"LAMBAYEQUE","PROV_HECHO":"CHICLAYO","DIST_HECHO":"JOSE LEONARDO ORTIZ","ID_MODALIDAD":"01120117","MODALIDAD":"PRODUCCION DE PELIGRO EN EL SERVICIO PUBLICO DE TRANSPORTE DE PASAJEROS","xx":-6.75,"yy":-79.85,"CASOS":57},{"ANIO":2025,"MES":7,"DPTO_HECHO":"LAMBAYEQUE","PROV_HECHO":"CHICLAYO","DIST_HECHO":"CHICLAYO","ID_MODALIDAD":"01050101","MODALIDAD":"HURTO","xx":-6.75,"yy":-79.85,"CASOS":43},{"ANIO":2025,"MES":8,"DPTO_HECHO":"LAMBAYEQUE","PROV_HECHO":"CHICLAYO","DIST_HECHO":"JOSE LEONARDO ORTIZ","ID_MODALIDAD":"01120117","MODALIDAD":"PRODUCCION DE PELIGRO EN EL SERVICIO PUBLICO DE TRANSPORTE DE PASAJEROS","xx":-6.75,"yy":-79.85,"CASOS":56},{"ANIO":2025,"MES":5,"DPTO_HECHO":"LAMBAYEQUE","PROV_HECHO":"CHICLAYO","DIST_HECHO":"JOSE LEONARDO ORTIZ","ID_MODALIDAD":"01120102","MODALIDAD":"CONDUCCION EN ESTADO DE EBRIEDAD O DROGADICCION","xx":-6.75,"yy":-79.8,"CASOS":27},{"ANIO":2025,"MES":5,"DPTO_HECHO":"LAMBAYEQUE","PROV_HECHO":"CHICLAYO","DIST_HECHO":"JOSE LEONARDO ORTIZ","ID_MODALIDAD":"01120102","MODALIDAD":"CONDUCCION EN ESTADO DE EBRIEDAD O DROGADICCION","xx":-6.75,"yy":-79.85,"CASOS":59},{"ANIO":2025,"MES":6,"DPTO_HECHO":"LAMBAYEQUE","PROV_HECHO":"CHICLAYO","DIST_HECHO":"CHICLAYO","ID_MODALIDAD":"01050101","MODALIDAD":"HURTO","xx":-6.75,"yy":-79.85,"CASOS":45},{"ANIO":2025,"MES":4,"DPTO_HECHO":"LAMBAYEQUE","PROV_HECHO":"CHICLAYO","DIST_HECHO":"CHICLAYO","ID_MODALIDAD":"01050101","MODALIDAD":"HURTO","xx":-6.75,"yy":-79.85,"CASOS":52},{"ANIO":2025,"MES":11,"DPTO_HECHO":"LAMBAYEQUE","PROV_HECHO":"CHICLAYO","DIST_HECHO":"CHICLAYO","ID_MODALIDAD":"01050101","MODALIDAD":"HURTO","xx":-6.75,"yy":-79.85,"CASOS":42},{"ANIO":2025,"MES":8,"DPTO_HECHO":"LAMBAYEQUE","PROV_HECHO":"CHICLAYO","DIST_HECHO":"CHICLAYO","ID_MODALIDAD":"01050119","MODALIDAD":"HURTO DE VEHICULO","xx":-6.75,"yy":-79.85,"CASOS":39},{"ANIO":2025,"MES":7,"DPTO_HECHO":"LAMBAYEQUE","PROV_HECHO":"CHICLAYO","DIST_HECHO":"JOSE LEONARDO ORTIZ","ID_MODALIDAD":"01120102","MODALIDAD":"CONDUCCION EN ESTADO DE EBRIEDAD O DROGADICCION","xx":-6.75,"yy":-79.85,"CASOS":37},{"ANIO":2025,"MES":8,"DPTO_HECHO":"LAMBAYEQUE","PROV_HECHO":"CHICLAYO","DIST_HECHO":"CHICLAYO","ID_MODALIDAD":"01120102","MODALIDAD":"CONDUCCION EN ESTADO DE EBRIEDAD O DROGADICCION","xx":-6.75,"yy":-79.8,"CASOS":31},{"ANIO":2025,"MES":6,"DPTO_HECHO":"LAMBAYEQUE","PROV_HECHO":"CHICLAYO","DIST_HECHO":"JOSE LEONARDO ORTIZ","ID_MODALIDAD":"01120102","MODALIDAD":"CONDUCCION EN ESTADO DE EBRIEDAD O DROGADICCION","xx":-6.75,"yy":-79.85,"CASOS":30},{"ANIO":2025,"MES":5,"DPTO_HECHO":"LAMBAYEQUE","PROV_HECHO":"CHICLAYO","DIST_HECHO":"CHICLAYO","ID_MODALIDAD":"01050101","MODALIDAD":"HURTO","xx":-6.75,"yy":-79.85,"CASOS":41},{"ANIO":2025,"MES":8,"DPTO_HECHO":"LAMBAYEQUE","PROV_HECHO":"CHICLAYO","DIST_HECHO":"CHICLAYO","ID_MODALIDAD":"01050101","MODALIDAD":"HURTO","xx":-6.75,"yy":-79.85,"CASOS":41},{"ANIO":2025,"MES":4,"DPTO_HECHO":"LAMBAYEQUE","PROV_HECHO":"CHICLAYO","DIST_HECHO":"CHICLAYO","ID_MODALIDAD":"01050501","MODALIDAD":"RECEPTACION","xx":-6.75,"yy":-79.85,"CASOS":25},{"ANIO":2025,"MES":7,"DPTO_HECHO":"LAMBAYEQUE","PROV_HECHO":"CHICLAYO","DIST_HECHO":"JOSE LEONARDO ORTIZ","ID_MODALIDAD":"01120102","MODALIDAD":"CONDUCCION EN ESTADO DE EBRIEDAD O DROGADICCION","xx":-6.75,"yy":-79.8,"CASOS":28},{"ANIO":2025,"MES":3,"DPTO_HECHO":"LAMBAYEQUE","PROV_HECHO":"CHICLAYO","DIST_HECHO":"JOSE LEONARDO ORTIZ","ID_MODALIDAD":"01120102","MODALIDAD":"CONDUCCION EN ESTADO DE EBRIEDAD O DROGADICCION","xx":-6.75,"yy":-79.85,"CASOS":24},{"ANIO":2025,"MES":4,"DPTO_HECHO":"LAMBAYEQUE","PROV_HECHO":"CHICLAYO","DIST_HECHO":"JOSE LEONARDO ORTIZ","ID_MODALIDAD":"01120102","MODALIDAD":"CONDUCCION EN ESTADO DE EBRIEDAD O DROGADICCION","xx":-6.75,"yy":-79.85,"CASOS":23},{"ANIO":2025,"MES":11,"DPTO_HECHO":"LAMBAYEQUE","PROV_HECHO":"CHICLAYO","DIST_HECHO":"CHICLAYO","ID_MODALIDAD":"01050601","MODALIDAD":"ESTAFA","xx":-6.75,"yy":-79.85,"CASOS":29},{"ANIO":2025,"MES":1,"DPTO_HECHO":"LAMBAYEQUE","PROV_HECHO":"CHICLAYO","DIST_HECHO":"JOSE LEONARDO ORTIZ","ID_MODALIDAD":"01120102","MODALIDAD":"CONDUCCION EN ESTADO DE EBRIEDAD O DROGADICCION","xx":-6.75,"yy":-79.85,"CASOS":26},{"ANIO":2025,"MES":3,"DPTO_HECHO":"LAMBAYEQUE","PROV_HECHO":"CHICLAYO","DIST_HECHO":"CHICLAYO","ID_MODALIDAD":"01050101","MODALIDAD":"HURTO","xx":-6.75,"yy":-79.85,"CASOS":47},{"ANIO":2025,"MES":10,"DPTO_HECHO":"LAMBAYEQUE","PROV_HECHO":"CHICLAYO","DIST_HECHO":"CHICLAYO","ID_MODALIDAD":"01050101","MODALIDAD":"HURTO","xx":-6.75,"yy":-79.85,"CASOS":33},{"ANIO":2025,"MES":9,"DPTO_HECHO":"LAMBAYEQUE","PROV_HECHO":"CHICLAYO","DIST_HECHO":"CHICLAYO","ID_MODALIDAD":"01050107","MODALIDAD":"HURTO AGRAVADO","xx":-6.8,"yy":-79.85,"CASOS":21},{"ANIO":2025,"MES":9,"DPTO_HECHO":"LAMBAYEQUE","PROV_HECHO":"CHICLAYO","DIST_HECHO":"CHICLAYO","ID_MODALIDAD":"01050107","MODALIDAD":"HURTO AGRAVADO","xx":-6.75,"yy":-79.85,"CASOS":30},{"ANIO":2025,"MES":10,"DPTO_HECHO":"LAMBAYEQUE","PROV_HECHO":"CHICLAYO","DIST_HECHO":"CHICLAYO","ID_MODALIDAD":"01120102","MODALIDAD":"CONDUCCION EN ESTADO DE EBRIEDAD O DROGADICCION","xx":-6.75,"yy":-79.8,"CASOS":15},{"ANIO":2025,"MES":8,"DPTO_HECHO":"LAMBAYEQUE","PROV_HECHO":"CHICLAYO","DIST_HECHO":"CHICLAYO","ID_MODALIDAD":"01120102","MODALIDAD":"CONDUCCION EN ESTADO DE EBRIEDAD O DROGADICCION","xx":-6.75,"yy":-79.85,"CASOS":43},{"ANIO":2025,"MES":2,"DPTO_HECHO":"LAMBAYEQUE","PROV_HECHO":"CHICLAYO","DIST_HECHO":"JOSE LEONARDO ORTIZ","ID_MODALIDAD":"01120102","MODALIDAD":"CONDUCCION EN ESTADO DE EBRIEDAD O DROGADICCION","xx":-6.75,"yy":-79.85,"CASOS":24},{"ANIO":2025,"MES":9,"DPTO_HECHO":"LAMBAYEQUE","PROV_HECHO":"CHICLAYO","DIST_HECHO":"JOSE LEONARDO ORTIZ","ID_MODALIDAD":"01120117","MODALIDAD":"PRODUCCION DE PELIGRO EN EL SERVICIO PUBLICO DE TRANSPORTE DE PASAJEROS","xx":-6.75,"yy":-79.85,"CASOS":22},{"ANIO":2025,"MES":4,"DPTO_HECHO":"LAMBAYEQUE","PROV_HECHO":"CHICLAYO","DIST_HECHO":"JOSE LEONARDO ORTIZ","ID_MODALIDAD":"01120102","MODALIDAD":"CONDUCCION EN ESTADO DE EBRIEDAD O DROGADICCION","xx":-6.75,"yy":-79.8,"CASOS":22},{"ANIO":2025,"MES":2,"DPTO_HECHO":"LAMBAYEQUE","PROV_HECHO":"CHICLAYO","DIST_HECHO":"CHICLAYO","ID_MODALIDAD":"01050101","MODALIDAD":"HURTO","xx":-6.75,"yy":-79.85,"CASOS":49},{"ANIO":2025,"MES":3,"DPTO_HECHO":"LAMBAYEQUE","PROV_HECHO":"CHICLAYO","DIST_HECHO":"JOSE LEONARDO ORTIZ","ID_MODALIDAD":"01120102","MODALIDAD":"CONDUCCION EN ESTADO DE EBRIEDAD O DROGADICCION","xx":-6.75,"yy":-79.8,"CASOS":18},{"ANIO":2025,"MES":9,"DPTO_HECHO":"LAMBAYEQUE","PROV_HECHO":"CHICLAYO","DIST_HECHO":"LA VICTORIA","ID_MODALIDAD":"01120102","MODALIDAD":"CONDUCCION EN ESTADO DE EBRIEDAD O DROGADICCION","xx":-6.8,"yy":-79.85,"CASOS":23},{"ANIO":2025,"MES":5,"DPTO_HECHO":"LAMBAYEQUE","PROV_HECHO":"CHICLAYO","DIST_HECHO":"JOSE LEONARDO ORTIZ","ID_MODALIDAD":"01050107","MODALIDAD":"HURTO AGRAVADO","xx":-6.75,"yy":-79.85,"CASOS":22},{"ANIO":2025,"MES":12,"DPTO_HECHO":"LAMBAYEQUE","PROV_HECHO":"CHICLAYO","DIST_HECHO":"CHICLAYO","ID_MODALIDAD":"01050119","MODALIDAD":"HURTO DE VEHICULO","xx":-6.75,"yy":-79.85,"CASOS":32},{"ANIO":2025,"MES":7,"DPTO_HECHO":"LAMBAYEQUE","PROV_HECHO":"CHICLAYO","DIST_HECHO":"CHICLAYO","ID_MODALIDAD":"01120102","MODALIDAD":"CONDUCCION EN ESTADO DE EBRIEDAD O DROGADICCION","xx":-6.75,"yy":-79.8,"CASOS":17},{"ANIO":2025,"MES":4,"DPTO_HECHO":"LAMBAYEQUE","PROV_HECHO":"CHICLAYO","DIST_HECHO":"CHICLAYO","ID_MODALIDAD":"01050101","MODALIDAD":"HURTO","xx":-6.8,"yy":-79.85,"CASOS":18},{"ANIO":2025,"MES":1,"DPTO_HECHO":"LAMBAYEQUE","PROV_HECHO":"CHICLAYO","DIST_HECHO":"JOSE LEONARDO ORTIZ","ID_MODALIDAD":"01120102","MODALIDAD":"CONDUCCION EN ESTADO DE EBRIEDAD O DROGADICCION","xx":-6.75,"yy":-79.8,"CASOS":15},{"ANIO":2025,"MES":6,"DPTO_HECHO":"LAMBAYEQUE","PROV_HECHO":"CHICLAYO","DIST_HECHO":"JOSE LEONARDO ORTIZ","ID_MODALIDAD":"01120102","MODALIDAD":"CONDUCCION EN ESTADO DE EBRIEDAD O DROGADICCION","xx":-6.75,"yy":-79.8,"CASOS":13},{"ANIO":2025,"MES":12,"DPTO_HECHO":"LAMBAYEQUE","PROV_HECHO":"CHICLAYO","DIST_HECHO":"JOSE LEONARDO ORTIZ","ID_MODALIDAD":"01120102","MODALIDAD":"CONDUCCION EN ESTADO DE EBRIEDAD O DROGADICCION","xx":-6.75,"yy":-79.85,"CASOS":40},{"ANIO":2025,"MES":5,"DPTO_HECHO":"LAMBAYEQUE","PROV_HECHO":"CHICLAYO","DIST_HECHO":"CHICLAYO","ID_MODALIDAD":"01050101","MODALIDAD":"HURTO","xx":-6.8,"yy":-79.85,"CASOS":15},{"ANIO":2025,"MES":12,"DPTO_HECHO":"LAMBAYEQUE","PROV_HECHO":"CHICLAYO","DIST_HECHO":"JOSE LEONARDO ORTIZ","ID_MODALIDAD":"05040202","MODALIDAD":"VIOLENCIA PSICOLOGICA","xx":-6.75,"yy":-79.85,"CASOS":38},{"ANIO":2025,"MES":9,"DPTO_HECHO":"LAMBAYEQUE","PROV_HECHO":"CHICLAYO","DIST_HECHO":"CHICLAYO","ID_MODALIDAD":"01050101","MODALIDAD":"HURTO","xx":-6.75,"yy":-79.85,"CASOS":22},{"ANIO":2025,"MES":12,"DPTO_HECHO":"LAMBAYEQUE","PROV_HECHO":"CHICLAYO","DIST_HECHO":"JOSE LEONARDO ORTIZ","ID_MODALIDAD":"01050101","MODALIDAD":"HURTO","xx":-6.75,"yy":-79.85,"CASOS":31},{"ANIO":2025,"MES":11,"DPTO_HECHO":"LAMBAYEQUE","PROV_HECHO":"CHICLAYO","DIST_HECHO":"LA VICTORIA","ID_MODALIDAD":"01120102","MODALIDAD":"CONDUCCION EN ESTADO DE EBRIEDAD O DROGADICCION","xx":-6.8,"yy":-79.85,"CASOS":22},{"ANIO":2025,"MES":3,"DPTO_HECHO":"LAMBAYEQUE","PROV_HECHO":"CHICLAYO","DIST_HECHO":"CHICLAYO","ID_MODALIDAD":"01120102","MODALIDAD":"CONDUCCION EN ESTADO DE EBRIEDAD O DROGADICCION","xx":-6.75,"yy":-79.8,"CASOS":18},{"ANIO":2025,"MES":12,"DPTO_HECHO":"LAMBAYEQUE","PROV_HECHO":"CHICLAYO","DIST_HECHO":"CHICLAYO","ID_MODALIDAD":"01050107","MODALIDAD":"HURTO AGRAVADO","xx":-6.75,"yy":-79.85,"CASOS":41},{"ANIO":2025,"MES":1,"DPTO_HECHO":"LAMBAYEQUE","PROV_HECHO":"CHICLAYO","DIST_HECHO":"CHICLAYO","ID_MODALIDAD":"01050101","MODALIDAD":"HURTO","xx":-6.75,"yy":-79.85,"CASOS":25},{"ANIO":2025,"MES":4,"DPTO_HECHO":"LAMBAYEQUE","PROV_HECHO":"CHICLAYO","DIST_HECHO":"CHICLAYO","ID_MODALIDAD":"01050107","MODALIDAD":"HURTO AGRAVADO","xx":-6.8,"yy":-79.85,"CASOS":19},{"ANIO":2025,"MES":1,"DPTO_HECHO":"LAMBAYEQUE","PROV_HECHO":"CHICLAYO","DIST_HECHO":"CHICLAYO","ID_MODALIDAD":"01050107","MODALIDAD":"HURTO AGRAVADO","xx":-6.8,"yy":-79.85,"CASOS":15},{"ANIO":2025,"MES":12,"DPTO_HECHO":"LAMBAYEQUE","PROV_HECHO":"LAMBAYEQUE","DIST_HECHO":"LAMBAYEQUE","ID_MODALIDAD":"01120117","MODALIDAD":"PRODUCCION DE PELIGRO EN EL SERVICIO PUBLICO DE TRANSPORTE DE PASAJEROS","xx":-6.7,"yy":-79.9,"CASOS":19},{"ANIO":2025,"MES":12,"DPTO_HECHO":"LAMBAYEQUE","PROV_HECHO":"CHICLAYO","DIST_HECHO":"CHICLAYO","ID_MODALIDAD":"01030401","MODALIDAD":"OMISION DE PRESTACION DE ALIMENTOS","xx":-6.75,"yy":-79.85,"CASOS":16},{"ANIO":2025,"MES":11,"DPTO_HECHO":"LAMBAYEQUE","PROV_HECHO":"CHICLAYO","DIST_HECHO":"CHICLAYO","ID_MODALIDAD":"01050101","MODALIDAD":"HURTO","xx":-6.8,"yy":-79.85,"CASOS":24},{"ANIO":2025,"MES":12,"DPTO_HECHO":"LAMBAYEQUE","PROV_HECHO":"CHICLAYO","DIST_HECHO":"CHICLAYO","ID_MODALIDAD":"01120102","MODALIDAD":"CONDUCCION EN ESTADO DE EBRIEDAD O DROGADICCION","xx":-6.75,"yy":-79.8,"CASOS":11},{"ANIO":2025,"MES":7,"DPTO_HECHO":"LAMBAYEQUE","PROV_HECHO":"CHICLAYO","DIST_HECHO":"LA VICTORIA","ID_MODALIDAD":"01120102","MODALIDAD":"CONDUCCION EN ESTADO DE EBRIEDAD O DROGADICCION","xx":-6.8,"yy":-79.85,"CASOS":24},{"ANIO":2025,"MES":7,"DPTO_HECHO":"LAMBAYEQUE","PROV_HECHO":"CHICLAYO","DIST_HECHO":"CHICLAYO","ID_MODALIDAD":"01050119","MODALIDAD":"HURTO DE VEHICULO","xx":-6.75,"yy":-79.85,"CASOS":16},{"ANIO":2025,"MES":10,"DPTO_HECHO":"LAMBAYEQUE","PROV_HECHO":"CHICLAYO","DIST_HECHO":"CHICLAYO","ID_MODALIDAD":"01050119","MODALIDAD":"HURTO DE VEHICULO","xx":-6.75,"yy":-79.85,"CASOS":17},{"ANIO":2025,"MES":7,"DPTO_HECHO":"LAMBAYEQUE","PROV_HECHO":"CHICLAYO","DIST_HECHO":"CHICLAYO","ID_MODALIDAD":"01050101","MODALIDAD":"HURTO","xx":-6.8,"yy":-79.85,"CASOS":16},{"ANIO":2025,"MES":10,"DPTO_HECHO":"LAMBAYEQUE","PROV_HECHO":"CHICLAYO","DIST_HECHO":"CHICLAYO","ID_MODALIDAD":"01120102","MODALIDAD":"CONDUCCION EN ESTADO DE EBRIEDAD O DROGADICCION","xx":-6.75,"yy":-79.85,"CASOS":27},{"ANIO":2025,"MES":11,"DPTO_HECHO":"LAMBAYEQUE","PROV_HECHO":"LAMBAYEQUE","DIST_HECHO":"LAMBAYEQUE","ID_MODALIDAD":"01120117","MODALIDAD":"PRODUCCION DE PELIGRO EN EL SERVICIO PUBLICO DE TRANSPORTE DE PASAJEROS","xx":-6.7,"yy":-79.9,"CASOS":12},{"ANIO":2025,"MES":9,"DPTO_HECHO":"LAMBAYEQUE","PROV_HECHO":"CHICLAYO","DIST_HECHO":"JOSE LEONARDO ORTIZ","ID_MODALIDAD":"01120102","MODALIDAD":"CONDUCCION EN ESTADO DE EBRIEDAD O DROGADICCION","xx":-6.75,"yy":-79.85,"CASOS":28},{"ANIO":2025,"MES":12,"DPTO_HECHO":"LAMBAYEQUE","PROV_HECHO":"FERREÑAFE","DIST_HECHO":"FERREÑAFE","ID_MODALIDAD":"05040202","MODALIDAD":"VIOLENCIA PSICOLOGICA","xx":-6.65,"yy":-79.8,"CASOS":18},{"ANIO":2025,"MES":12,"DPTO_HECHO":"LAMBAYEQUE","PROV_HECHO":"CHICLAYO","DIST_HECHO":"JOSE LEONARDO ORTIZ","ID_MODALIDAD":"01050107","MODALIDAD":"HURTO AGRAVADO","xx":-6.75,"yy":-79.85,"CASOS":23},{"ANIO":2025,"MES":5,"DPTO_HECHO":"LAMBAYEQUE","PROV_HECHO":"CHICLAYO","DIST_HECHO":"CHICLAYO","ID_MODALIDAD":"01050501","MODALIDAD":"RECEPTACION","xx":-6.75,"yy":-79.85,"CASOS":11},{"ANIO":2025,"MES":2,"DPTO_HECHO":"LAMBAYEQUE","PROV_HECHO":"FERREÑAFE","DIST_HECHO":"FERREÑAFE","ID_MODALIDAD":"01120102","MODALIDAD":"CONDUCCION EN ESTADO DE EBRIEDAD O DROGADICCION","xx":-6.65,"yy":-79.8,"CASOS":16},{"ANIO":2025,"MES":3,"DPTO_HECHO":"LAMBAYEQUE","PROV_HECHO":"CHICLAYO","DIST_HECHO":"CHICLAYO","ID_MODALIDAD":"01050107","MODALIDAD":"HURTO AGRAVADO","xx":-6.75,"yy":-79.85,"CASOS":18},{"ANIO":2025,"MES":12,"DPTO_HECHO":"LAMBAYEQUE","PROV_HECHO":"CHICLAYO","DIST_HECHO":"LA VICTORIA","ID_MODALIDAD":"01120102","MODALIDAD":"CONDUCCION EN ESTADO DE EBRIEDAD O DROGADICCION","xx":-6.8,"yy":-79.85,"CASOS":23},{"ANIO":2025,"MES":12,"DPTO_HECHO":"LAMBAYEQUE","PROV_HECHO":"CHICLAYO","DIST_HECHO":"CHICLAYO","ID_MODALIDAD":"01050101","MODALIDAD":"HURTO","xx":-6.8,"yy":-79.85,"CASOS":28},{"ANIO":2025,"MES":3,"DPTO_HECHO":"LAMBAYEQUE","PROV_HECHO":"CHICLAYO","DIST_HECHO":"CHICLAYO","ID_MODALIDAD":"01120102","MODALIDAD":"CONDUCCION EN ESTADO DE EBRIEDAD O DROGADICCION","xx":-6.75,"yy":-79.85,"CASOS":10},{"ANIO":2025,"MES":4,"DPTO_HECHO":"LAMBAYEQUE","PROV_HECHO":"CHICLAYO","DIST_HECHO":"LA VICTORIA","ID_MODALIDAD":"01120102","MODALIDAD":"CONDUCCION EN ESTADO DE EBRIEDAD O DROGADICCION","xx":-6.8,"yy":-79.85,"CASOS":20},{"ANIO":2025,"MES":12,"DPTO_HECHO":"LAMBAYEQUE","PROV_HECHO":"CHICLAYO","DIST_HECHO":"CHICLAYO","ID_MODALIDAD":"01050601","MODALIDAD":"ESTAFA","xx":-6.75,"yy":-79.85,"CASOS":19},{"ANIO":2025,"MES":7,"DPTO_HECHO":"LAMBAYEQUE","PROV_HECHO":"CHICLAYO","DIST_HECHO":"CHICLAYO","ID_MODALIDAD":"01050107","MODALIDAD":"HURTO AGRAVADO","xx":-6.75,"yy":-79.85,"CASOS":16},{"ANIO":2025,"MES":3,"DPTO_HECHO":"LAMBAYEQUE","PROV_HECHO":"CHICLAYO","DIST_HECHO":"CHICLAYO","ID_MODALIDAD":"01050501","MODALIDAD":"RECEPTACION","xx":-6.75,"yy":-79.85,"CASOS":9},{"ANIO":2025,"MES":10,"DPTO_HECHO":"LAMBAYEQUE","PROV_HECHO":"CHICLAYO","DIST_HECHO":"JOSE LEONARDO ORTIZ","ID_MODALIDAD":"01050107","MODALIDAD":"HURTO AGRAVADO","xx":-6.75,"yy":-79.85,"CASOS":19},{"ANIO":2025,"MES":8,"DPTO_HECHO":"LAMBAYEQUE","PROV_HECHO":"CHICLAYO","DIST_HECHO":"CHICLAYO","ID_MODALIDAD":"01050107","MODALIDAD":"HURTO AGRAVADO","xx":-6.75,"yy":-79.85,"CASOS":24},{"ANIO":2025,"MES":5,"DPTO_HECHO":"LAMBAYEQUE","PROV_HECHO":"CHICLAYO","DIST_HECHO":"CHICLAYO","ID_MODALIDAD":"01120102","MODALIDAD":"CONDUCCION EN ESTADO DE EBRIEDAD O DROGADICCION","xx":-6.75,"yy":-79.8,"CASOS":10},{"ANIO":2025,"MES":6,"DPTO_HECHO":"LAMBAYEQUE","PROV_HECHO":"CHICLAYO","DIST_HECHO":"CHICLAYO","ID_MODALIDAD":"01050101","MODALIDAD":"HURTO","xx":-6.8,"yy":-79.85,"CASOS":13},{"ANIO":2025,"MES":9,"DPTO_HECHO":"LAMBAYEQUE","PROV_HECHO":"CHICLAYO","DIST_HECHO":"CHICLAYO","ID_MODALIDAD":"01050601","MODALIDAD":"ESTAFA","xx":-6.75,"yy":-79.85,"CASOS":8},{"ANIO":2025,"MES":10,"DPTO_HECHO":"LAMBAYEQUE","PROV_HECHO":"CHICLAYO","DIST_HECHO":"CAYALTI","ID_MODALIDAD":"05040202","MODALIDAD":"VIOLENCIA PSICOLOGICA","xx":-6.9,"yy":-79.55,"CASOS":9},{"ANIO":2025,"MES":12,"DPTO_HECHO":"LAMBAYEQUE","PROV_HECHO":"CHICLAYO","DIST_HECHO":"CHICLAYO","ID_MODALIDAD":"05040202","MODALIDAD":"VIOLENCIA PSICOLOGICA","xx":-6.75,"yy":-79.8,"CASOS":11},{"ANIO":2025,"MES":11,"DPTO_HECHO":"LAMBAYEQUE","PROV_HECHO":"CHICLAYO","DIST_HECHO":"CHICLAYO","ID_MODALIDAD":"01050107","MODALIDAD":"HURTO AGRAVADO","xx":-6.75,"yy":-79.85,"CASOS":16},{"ANIO":2025,"MES":8,"DPTO_HECHO":"LAMBAYEQUE","PROV_HECHO":"CHICLAYO","DIST_HECHO":"JOSE LEONARDO ORTIZ","ID_MODALIDAD":"01050119","MODALIDAD":"HURTO DE VEHICULO","xx":-6.75,"yy":-79.85,"CASOS":17},{"ANIO":2025,"MES":11,"DPTO_HECHO":"LAMBAYEQUE","PROV_HECHO":"FERREÑAFE","DIST_HECHO":"PUEBLO NUEVO","ID_MODALIDAD":"05040202","MODALIDAD":"VIOLENCIA PSICOLOGICA","xx":-6.65,"yy":-79.8,"CASOS":8},{"ANIO":2025,"MES":1,"DPTO_HECHO":"LAMBAYEQUE","PROV_HECHO":"CHICLAYO","DIST_HECHO":"JOSE LEONARDO ORTIZ","ID_MODALIDAD":"01050101","MODALIDAD":"HURTO","xx":-6.75,"yy":-79.85,"CASOS":14},{"ANIO":2025,"MES":8,"DPTO_HECHO":"LAMBAYEQUE","PROV_HECHO":"CHICLAYO","DIST_HECHO":"CHICLAYO","ID_MODALIDAD":"01050101","MODALIDAD":"HURTO","xx":-6.8,"yy":-79.85,"CASOS":16},{"ANIO":2025,"MES":1,"DPTO_HECHO":"LAMBAYEQUE","PROV_HECHO":"CHICLAYO","DIST_HECHO":"LA VICTORIA","ID_MODALIDAD":"05040202","MODALIDAD":"VIOLENCIA PSICOLOGICA","xx":-6.8,"yy":-79.85,"CASOS":13},{"ANIO":2025,"MES":6,"DPTO_HECHO":"LAMBAYEQUE","PROV_HECHO":"CHICLAYO","DIST_HECHO":"CHICLAYO","ID_MODALIDAD":"01120102","MODALIDAD":"CONDUCCION EN ESTADO DE EBRIEDAD O DROGADICCION","xx":-6.75,"yy":-79.85,"CASOS":12},{"ANIO":2025,"MES":6,"DPTO_HECHO":"LAMBAYEQUE","PROV_HECHO":"CHICLAYO","DIST_HECHO":"LA VICTORIA","ID_MODALIDAD":"01120102","MODALIDAD":"CONDUCCION EN ESTADO DE EBRIEDAD O DROGADICCION","xx":-6.8,"yy":-79.85,"CASOS":15},{"ANIO":2025,"MES":12,"DPTO_HECHO":"LAMBAYEQUE","PROV_HECHO":"CHICLAYO","DIST_HECHO":"CHICLAYO","ID_MODALIDAD":"05040202","MODALIDAD":"VIOLENCIA PSICOLOGICA","xx":-6.75,"yy":-79.85,"CASOS":27},{"ANIO":2025,"MES":2,"DPTO_HECHO":"LAMBAYEQUE","PROV_HECHO":"CHICLAYO","DIST_HECHO":"JOSE LEONARDO ORTIZ","ID_MODALIDAD":"01120102","MODALIDAD":"CONDUCCION EN ESTADO DE EBRIEDAD O DROGADICCION","xx":-6.75,"yy":-79.8,"CASOS":13},{"ANIO":2025,"MES":8,"DPTO_HECHO":"LAMBAYEQUE","PROV_HECHO":"CHICLAYO","DIST_HECHO":"JOSE LEONARDO ORTIZ","ID_MODALIDAD":"01050107","MODALIDAD":"HURTO AGRAVADO","xx":-6.75,"yy":-79.85,"CASOS":13},{"ANIO":2025,"MES":11,"DPTO_HECHO":"LAMBAYEQUE","PROV_HECHO":"CHICLAYO","DIST_HECHO":"JOSE LEONARDO ORTIZ","ID_MODALIDAD":"01120102","MODALIDAD":"CONDUCCION EN ESTADO DE EBRIEDAD O DROGADICCION","xx":-6.75,"yy":-79.85,"CASOS":16},{"ANIO":2025,"MES":12,"DPTO_HECHO":"LAMBAYEQUE","PROV_HECHO":"CHICLAYO","DIST_HECHO":"CHICLAYO","ID_MODALIDAD":"01050107","MODALIDAD":"HURTO AGRAVADO","xx":-6.8,"yy":-79.85,"CASOS":17},{"ANIO":2025,"MES":4,"DPTO_HECHO":"LAMBAYEQUE","PROV_HECHO":"CHICLAYO","DIST_HECHO":"CHICLAYO","ID_MODALIDAD":"01050107","MODALIDAD":"HURTO AGRAVADO","xx":-6.75,"yy":-79.85,"CASOS":20},{"ANIO":2025,"MES":1,"DPTO_HECHO":"LAMBAYEQUE","PROV_HECHO":"CHICLAYO","DIST_HECHO":"CHICLAYO","ID_MODALIDAD":"01050107","MODALIDAD":"HURTO AGRAVADO","xx":-6.75,"yy":-79.85,"CASOS":11},{"ANIO":2025,"MES":6,"DPTO_HECHO":"LAMBAYEQUE","PROV_HECHO":"CHICLAYO","DIST_HECHO":"JOSE LEONARDO ORTIZ","ID_MODALIDAD":"01050107","MODALIDAD":"HURTO AGRAVADO","xx":-6.75,"yy":-79.85,"CASOS":14},{"ANIO":2025,"MES":12,"DPTO_HECHO":"LAMBAYEQUE","PROV_HECHO":"CHICLAYO","DIST_HECHO":"LA VICTORIA","ID_MODALIDAD":"01050119","MODALIDAD":"HURTO DE VEHICULO","xx":-6.8,"yy":-79.85,"CASOS":7},{"ANIO":2025,"MES":7,"DPTO_HECHO":"LAMBAYEQUE","PROV_HECHO":"FERREÑAFE","DIST_HECHO":"FERREÑAFE","ID_MODALIDAD":"05040202","MODALIDAD":"VIOLENCIA PSICOLOGICA","xx":-6.65,"yy":-79.8,"CASOS":10},{"ANIO":2025,"MES":6,"DPTO_HECHO":"LAMBAYEQUE","PROV_HECHO":"CHICLAYO","DIST_HECHO":"CHICLAYO","ID_MODALIDAD":"01050107","MODALIDAD":"HURTO AGRAVADO","xx":-6.75,"yy":-79.85,"CASOS":20},{"ANIO":2025,"MES":11,"DPTO_HECHO":"LAMBAYEQUE","PROV_HECHO":"CHICLAYO","DIST_HECHO":"CHICLAYO","ID_MODALIDAD":"01120102","MODALIDAD":"CONDUCCION EN ESTADO DE EBRIEDAD O DROGADICCION","xx":-6.75,"yy":-79.8,"CASOS":6},{"ANIO":2025,"MES":3,"DPTO_HECHO":"LAMBAYEQUE","PROV_HECHO":"CHICLAYO","DIST_HECHO":"CHICLAYO","ID_MODALIDAD":"01050101","MODALIDAD":"HURTO","xx":-6.8,"yy":-79.85,"CASOS":19},{"ANIO":2025,"MES":5,"DPTO_HECHO":"LAMBAYEQUE","PROV_HECHO":"CHICLAYO","DIST_HECHO":"CHICLAYO","ID_MODALIDAD":"01120102","MODALIDAD":"CONDUCCION EN ESTADO DE EBRIEDAD O DROGADICCION","xx":-6.8,"yy":-79.85,"CASOS":11},{"ANIO":2025,"MES":7,"DPTO_HECHO":"LAMBAYEQUE","PROV_HECHO":"CHICLAYO","DIST_HECHO":"CHICLAYO","ID_MODALIDAD":"05040202","MODALIDAD":"VIOLENCIA PSICOLOGICA","xx":-6.75,"yy":-79.85,"CASOS":10},{"ANIO":2025,"MES":10,"DPTO_HECHO":"LAMBAYEQUE","PROV_HECHO":"FERREÑAFE","DIST_HECHO":"FERREÑAFE","ID_MODALIDAD":"01120102","MODALIDAD":"CONDUCCION EN ESTADO DE EBRIEDAD O DROGADICCION","xx":-6.65,"yy":-79.8,"CASOS":11},{"ANIO":2025,"MES":8,"DPTO_HECHO":"LAMBAYEQUE","PROV_HECHO":"CHICLAYO","DIST_HECHO":"LA VICTORIA","ID_MODALIDAD":"01050119","MODALIDAD":"HURTO DE VEHICULO","xx":-6.8,"yy":-79.85,"CASOS":14},{"ANIO":2025,"MES":10,"DPTO_HECHO":"LAMBAYEQUE","PROV_HECHO":"CHICLAYO","DIST_HECHO":"JOSE LEONARDO ORTIZ","ID_MODALIDAD":"01050101","MODALIDAD":"HURTO","xx":-6.75,"yy":-79.85,"CASOS":18},{"ANIO":2025,"MES":1,"DPTO_HECHO":"LAMBAYEQUE","PROV_HECHO":"CHICLAYO","DIST_HECHO":"JOSE LEONARDO ORTIZ","ID_MODALIDAD":"01050501","MODALIDAD":"RECEPTACION","xx":-6.75,"yy":-79.85,"CASOS":15},{"ANIO":2025,"MES":9,"DPTO_HECHO":"LAMBAYEQUE","PROV_HECHO":"CHICLAYO","DIST_HECHO":"CHICLAYO","ID_MODALIDAD":"01050119","MODALIDAD":"HURTO DE VEHICULO","xx":-6.75,"yy":-79.85,"CASOS":18},{"ANIO":2025,"MES":1,"DPTO_HECHO":"LAMBAYEQUE","PROV_HECHO":"CHICLAYO","DIST_HECHO":"CHICLAYO","ID_MODALIDAD":"01050601","MODALIDAD":"ESTAFA","xx":-6.75,"yy":-79.85,"CASOS":12},{"ANIO":2025,"MES":9,"DPTO_HECHO":"LAMBAYEQUE","PROV_HECHO":"CHICLAYO","DIST_HECHO":"JOSE LEONARDO ORTIZ","ID_MODALIDAD":"01050107","MODALIDAD":"HURTO AGRAVADO","xx":-6.75,"yy":-79.85,"CASOS":16},{"ANIO":2025,"MES":12,"DPTO_HECHO":"LAMBAYEQUE","PROV_HECHO":"CHICLAYO","DIST_HECHO":"CHICLAYO","ID_MODALIDAD":"01050119","MODALIDAD":"HURTO DE VEHICULO","xx":-6.8,"yy":-79.85,"CASOS":12},{"ANIO":2025,"MES":12,"DPTO_HECHO":"LAMBAYEQUE","PROV_HECHO":"CHICLAYO","DIST_HECHO":"LA VICTORIA","ID_MODALIDAD":"01050101","MODALIDAD":"HURTO","xx":-6.8,"yy":-79.85,"CASOS":18},{"ANIO":2025,"MES":12,"DPTO_HECHO":"LAMBAYEQUE","PROV_HECHO":"CHICLAYO","DIST_HECHO":"LA VICTORIA","ID_MODALIDAD":"01050201","MODALIDAD":"ROBO","xx":-6.8,"yy":-79.85,"CASOS":6},{"ANIO":2025,"MES":6,"DPTO_HECHO":"LAMBAYEQUE","PROV_HECHO":"CHICLAYO","DIST_HECHO":"JOSE LEONARDO ORTIZ","ID_MODALIDAD":"01050101","MODALIDAD":"HURTO","xx":-6.75,"yy":-79.85,"CASOS":11},{"ANIO":2025,"MES":5,"DPTO_HECHO":"LAMBAYEQUE","PROV_HECHO":"CHICLAYO","DIST_HECHO":"CHICLAYO","ID_MODALIDAD":"01050107","MODALIDAD":"HURTO AGRAVADO","xx":-6.75,"yy":-79.85,"CASOS":17},{"ANIO":2025,"MES":7,"DPTO_HECHO":"LAMBAYEQUE","PROV_HECHO":"CHICLAYO","DIST_HECHO":"JOSE LEONARDO ORTIZ","ID_MODALIDAD":"01300501","MODALIDAD":"FALTAS CONTRA LA SEGURIDAD PUBLICA","xx":-6.75,"yy":-79.85,"CASOS":8},{"ANIO":2025,"MES":9,"DPTO_HECHO":"LAMBAYEQUE","PROV_HECHO":"FERREÑAFE","DIST_HECHO":"FERREÑAFE","ID_MODALIDAD":"01120102","MODALIDAD":"CONDUCCION EN ESTADO DE EBRIEDAD O DROGADICCION","xx":-6.65,"yy":-79.8,"CASOS":8},{"ANIO":2025,"MES":1,"DPTO_HECHO":"LAMBAYEQUE","PROV_HECHO":"CHICLAYO","DIST_HECHO":"JOSE LEONARDO ORTIZ","ID_MODALIDAD":"01050107","MODALIDAD":"HURTO AGRAVADO","xx":-6.75,"yy":-79.85,"CASOS":15},{"ANIO":2025,"MES":5,"DPTO_HECHO":"LAMBAYEQUE","PROV_HECHO":"CHICLAYO","DIST_HECHO":"JOSE LEONARDO ORTIZ","ID_MODALIDAD":"01050501","MODALIDAD":"RECEPTACION","xx":-6.75,"yy":-79.85,"CASOS":13},{"ANIO":2025,"MES":5,"DPTO_HECHO":"LAMBAYEQUE","PROV_HECHO":"FERREÑAFE","DIST_HECHO":"FERREÑAFE","ID_MODALIDAD":"05040202","MODALIDAD":"VIOLENCIA PSICOLOGICA","xx":-6.65,"yy":-79.8,"CASOS":7},{"ANIO":2025,"MES":7,"DPTO_HECHO":"LAMBAYEQUE","PROV_HECHO":"CHICLAYO","DIST_HECHO":"CHICLAYO","ID_MODALIDAD":"01120117","MODALIDAD":"PRODUCCION DE PELIGRO EN EL SERVICIO PUBLICO DE TRANSPORTE DE PASAJEROS","xx":-6.75,"yy":-79.85,"CASOS":10},{"ANIO":2025,"MES":2,"DPTO_HECHO":"LAMBAYEQUE","PROV_HECHO":"CHICLAYO","DIST_HECHO":"CHICLAYO","ID_MODALIDAD":"01120102","MODALIDAD":"CONDUCCION EN ESTADO DE EBRIEDAD O DROGADICCION","xx":-6.75,"yy":-79.8,"CASOS":9},{"ANIO":2025,"MES":2,"DPTO_HECHO":"LAMBAYEQUE","PROV_HECHO":"LAMBAYEQUE","DIST_HECHO":"MOTUPE","ID_MODALIDAD":"01120102","MODALIDAD":"CONDUCCION EN ESTADO DE EBRIEDAD O DROGADICCION","xx":-6.15,"yy":-79.7,"CASOS":7},{"ANIO":2025,"MES":12,"DPTO_HECHO":"LAMBAYEQUE","PROV_HECHO":"CHICLAYO","DIST_HECHO":"LA VICTORIA","ID_MODALIDAD":"05040202","MODALIDAD":"VIOLENCIA PSICOLOGICA","xx":-6.8,"yy":-79.85,"CASOS":14},{"ANIO":2025,"MES":7,"DPTO_HECHO":"LAMBAYEQUE","PROV_HECHO":"CHICLAYO","DIST_HECHO":"JOSE LEONARDO ORTIZ","ID_MODALIDAD":"05040202","MODALIDAD":"VIOLENCIA PSICOLOGICA","xx":-6.75,"yy":-79.85,"CASOS":12},{"ANIO":2025,"MES":4,"DPTO_HECHO":"LAMBAYEQUE","PROV_HECHO":"CHICLAYO","DIST_HECHO":"CHICLAYO","ID_MODALIDAD":"01050601","MODALIDAD":"ESTAFA","xx":-6.75,"yy":-79.85,"CASOS":7},{"ANIO":2025,"MES":8,"DPTO_HECHO":"LAMBAYEQUE","PROV_HECHO":"FERREÑAFE","DIST_HECHO":"FERREÑAFE","ID_MODALIDAD":"05040202","MODALIDAD":"VIOLENCIA PSICOLOGICA","xx":-6.65,"yy":-79.8,"CASOS":10},{"ANIO":2025,"MES":7,"DPTO_HECHO":"LAMBAYEQUE","PROV_HECHO":"CHICLAYO","DIST_HECHO":"CHICLAYO","ID_MODALIDAD":"01120102","MODALIDAD":"CONDUCCION EN ESTADO DE EBRIEDAD O DROGADICCION","xx":-6.75,"yy":-79.85,"CASOS":8},{"ANIO":2025,"MES":2,"DPTO_HECHO":"LAMBAYEQUE","PROV_HECHO":"CHICLAYO","DIST_HECHO":"CHICLAYO","ID_MODALIDAD":"05040202","MODALIDAD":"VIOLENCIA PSICOLOGICA","xx":-6.75,"yy":-79.85,"CASOS":14},{"ANIO":2025,"MES":12,"DPTO_HECHO":"LAMBAYEQUE","PROV_HECHO":"CHICLAYO","DIST_HECHO":"JOSE LEONARDO ORTIZ","ID_MODALIDAD":"01050601","MODALIDAD":"ESTAFA","xx":-6.75,"yy":-79.85,"CASOS":8},{"ANIO":2025,"MES":12,"DPTO_HECHO":"LAMBAYEQUE","PROV_HECHO":"CHICLAYO","DIST_HECHO":"CHICLAYO","ID_MODALIDAD":"01050122","MODALIDAD":"HURTO DE CELULAR","xx":-6.75,"yy":-79.85,"CASOS":6},{"ANIO":2025,"MES":1,"DPTO_HECHO":"LAMBAYEQUE","PROV_HECHO":"CHICLAYO","DIST_HECHO":"LA VICTORIA","ID_MODALIDAD":"05040201","MODALIDAD":"VIOLENCIA FISICA","xx":-6.8,"yy":-79.85,"CASOS":7},{"ANIO":2025,"MES":8,"DPTO_HECHO":"LAMBAYEQUE","PROV_HECHO":"CHICLAYO","DIST_HECHO":"TUMAN","ID_MODALIDAD":"01120102","MODALIDAD":"CONDUCCION EN ESTADO DE EBRIEDAD O DROGADICCION","xx":-6.8,"yy":-79.7,"CASOS":7},{"ANIO":2025,"MES":11,"DPTO_HECHO":"LAMBAYEQUE","PROV_HECHO":"CHICLAYO","DIST_HECHO":"JOSE LEONARDO ORTIZ","ID_MODALIDAD":"01050107","MODALIDAD":"HURTO AGRAVADO","xx":-6.75,"yy":-79.85,"CASOS":12},{"ANIO":2025,"MES":2,"DPTO_HECHO":"LAMBAYEQUE","PROV_HECHO":"CHICLAYO","DIST_HECHO":"CHICLAYO","ID_MODALIDAD":"01050107","MODALIDAD":"HURTO AGRAVADO","xx":-6.75,"yy":-79.85,"CASOS":14},{"ANIO":2025,"MES":12,"DPTO_HECHO":"LAMBAYEQUE","PROV_HECHO":"CHICLAYO","DIST_HECHO":"CAYALTI","ID_MODALIDAD":"05040202","MODALIDAD":"VIOLENCIA PSICOLOGICA","xx":-6.9,"yy":-79.55,"CASOS":8},{"ANIO":2025,"MES":3,"DPTO_HECHO":"LAMBAYEQUE","PROV_HECHO":"CHICLAYO","DIST_HECHO":"LA VICTORIA","ID_MODALIDAD":"01120102","MODALIDAD":"CONDUCCION EN ESTADO DE EBRIEDAD O DROGADICCION","xx":-6.8,"yy":-79.85,"CASOS":12},{"ANIO":2025,"MES":6,"DPTO_HECHO":"LAMBAYEQUE","PROV_HECHO":"CHICLAYO","DIST_HECHO":"CHICLAYO","ID_MODALIDAD":"01050501","MODALIDAD":"RECEPTACION","xx":-6.75,"yy":-79.85,"CASOS":8},{"ANIO":2025,"MES":12,"DPTO_HECHO":"LAMBAYEQUE","PROV_HECHO":"CHICLAYO","DIST_HECHO":"CHICLAYO","ID_MODALIDAD":"01050101","MODALIDAD":"HURTO","xx":-6.8,"yy":-79.9,"CASOS":8},{"ANIO":2025,"MES":11,"DPTO_HECHO":"LAMBAYEQUE","PROV_HECHO":"CHICLAYO","DIST_HECHO":"CHICLAYO","ID_MODALIDAD":"05080401","MODALIDAD":"FRAUDE INFORMATICO","xx":-6.75,"yy":-79.85,"CASOS":20},{"ANIO":2025,"MES":2,"DPTO_HECHO":"LAMBAYEQUE","PROV_HECHO":"CHICLAYO","DIST_HECHO":"CHICLAYO","ID_MODALIDAD":"01050101","MODALIDAD":"HURTO","xx":-6.8,"yy":-79.85,"CASOS":13},{"ANIO":2025,"MES":5,"DPTO_HECHO":"LAMBAYEQUE","PROV_HECHO":"CHICLAYO","DIST_HECHO":"CHICLAYO","ID_MODALIDAD":"01120102","MODALIDAD":"CONDUCCION EN ESTADO DE EBRIEDAD O DROGADICCION","xx":-6.75,"yy":-79.85,"CASOS":6},{"ANIO":2025,"MES":12,"DPTO_HECHO":"LAMBAYEQUE","PROV_HECHO":"CHICLAYO","DIST_HECHO":"JOSE LEONARDO ORTIZ","ID_MODALIDAD":"01120102","MODALIDAD":"CONDUCCION EN ESTADO DE EBRIEDAD O DROGADICCION","xx":-6.75,"yy":-79.8,"CASOS":7},{"ANIO":2025,"MES":12,"DPTO_HECHO":"LAMBAYEQUE","PROV_HECHO":"FERREÑAFE","DIST_HECHO":"FERREÑAFE","ID_MODALIDAD":"01050101","MODALIDAD":"HURTO","xx":-6.65,"yy":-79.8,"CASOS":8},{"ANIO":2025,"MES":12,"DPTO_HECHO":"LAMBAYEQUE","PROV_HECHO":"CHICLAYO","DIST_HECHO":"CHICLAYO","ID_MODALIDAD":"01050215","MODALIDAD":"ROBO AGRAVADO","xx":-6.8,"yy":-79.85,"CASOS":13},{"ANIO":2025,"MES":11,"DPTO_HECHO":"LAMBAYEQUE","PROV_HECHO":"CHICLAYO","DIST_HECHO":"CHICLAYO","ID_MODALIDAD":"01050119","MODALIDAD":"HURTO DE VEHICULO","xx":-6.75,"yy":-79.85,"CASOS":11},{"ANIO":2025,"MES":8,"DPTO_HECHO":"LAMBAYEQUE","PROV_HECHO":"CHICLAYO","DIST_HECHO":"JOSE LEONARDO ORTIZ","ID_MODALIDAD":"01120102","MODALIDAD":"CONDUCCION EN ESTADO DE EBRIEDAD O DROGADICCION","xx":-6.75,"yy":-79.85,"CASOS":19},{"ANIO":2025,"MES":11,"DPTO_HECHO":"LAMBAYEQUE","PROV_HECHO":"CHICLAYO","DIST_HECHO":"CHICLAYO","ID_MODALIDAD":"01030401","MODALIDAD":"OMISION DE PRESTACION DE ALIMENTOS","xx":-6.75,"yy":-79.85,"CASOS":8},{"ANIO":2025,"MES":2,"DPTO_HECHO":"LAMBAYEQUE","PROV_HECHO":"CHICLAYO","DIST_HECHO":"CHICLAYO","ID_MODALIDAD":"01300201","MODALIDAD":"LESION DOLOSA","xx":-6.75,"yy":-79.85,"CASOS":6},{"ANIO":2025,"MES":11,"DPTO_HECHO":"LAMBAYEQUE","PROV_HECHO":"CHICLAYO","DIST_HECHO":"JOSE LEONARDO ORTIZ","ID_MODALIDAD":"05040202","MODALIDAD":"VIOLENCIA PSICOLOGICA","xx":-6.75,"yy":-79.85,"CASOS":19},{"ANIO":2025,"MES":3,"DPTO_HECHO":"LAMBAYEQUE","PROV_HECHO":"CHICLAYO","DIST_HECHO":"CHICLAYO","ID_MODALIDAD":"01050107","MODALIDAD":"HURTO AGRAVADO","xx":-6.8,"yy":-79.85,"CASOS":9},{"ANIO":2025,"MES":11,"DPTO_HECHO":"LAMBAYEQUE","PROV_HECHO":"CHICLAYO","DIST_HECHO":"CHICLAYO","ID_MODALIDAD":"01120102","MODALIDAD":"CONDUCCION EN ESTADO DE EBRIEDAD O DROGADICCION","xx":-6.75,"yy":-79.85,"CASOS":14},{"ANIO":2025,"MES":12,"DPTO_HECHO":"LAMBAYEQUE","PROV_HECHO":"CHICLAYO","DIST_HECHO":"CHICLAYO","ID_MODALIDAD":"01050215","MODALIDAD":"ROBO AGRAVADO","xx":-6.75,"yy":-79.85,"CASOS":12},{"ANIO":2025,"MES":11,"DPTO_HECHO":"LAMBAYEQUE","PROV_HECHO":"CHICLAYO","DIST_HECHO":"CHICLAYO","ID_MODALIDAD":"01050201","MODALIDAD":"ROBO","xx":-6.75,"yy":-79.85,"CASOS":6},{"ANIO":2025,"MES":8,"DPTO_HECHO":"LAMBAYEQUE","PROV_HECHO":"CHICLAYO","DIST_HECHO":"JOSE LEONARDO ORTIZ","ID_MODALIDAD":"01050101","MODALIDAD":"HURTO","xx":-6.75,"yy":-79.85,"CASOS":19},{"ANIO":2025,"MES":10,"DPTO_HECHO":"LAMBAYEQUE","PROV_HECHO":"CHICLAYO","DIST_HECHO":"CHICLAYO","ID_MODALIDAD":"01300201","MODALIDAD":"LESION DOLOSA","xx":-6.75,"yy":-79.85,"CASOS":5},{"ANIO":2025,"MES":12,"DPTO_HECHO":"LAMBAYEQUE","PROV_HECHO":"CHICLAYO","DIST_HECHO":"CHICLAYO","ID_MODALIDAD":"01300201","MODALIDAD":"LESION DOLOSA","xx":-6.75,"yy":-79.85,"CASOS":8},{"ANIO":2025,"MES":3,"DPTO_HECHO":"LAMBAYEQUE","PROV_HECHO":"CHICLAYO","DIST_HECHO":"CHICLAYO","ID_MODALIDAD":"01050122","MODALIDAD":"HURTO DE CELULAR","xx":-6.75,"yy":-79.85,"CASOS":9},{"ANIO":2025,"MES":6,"DPTO_HECHO":"LAMBAYEQUE","PROV_HECHO":"CHICLAYO","DIST_HECHO":"CHICLAYO","ID_MODALIDAD":"01300207","MODALIDAD":"AGRESION SIN DAÑO","xx":-6.75,"yy":-79.85,"CASOS":5},{"ANIO":2025,"MES":5,"DPTO_HECHO":"LAMBAYEQUE","PROV_HECHO":"CHICLAYO","DIST_HECHO":"JOSE LEONARDO ORTIZ","ID_MODALIDAD":"01010316","MODALIDAD":"LESIONES","xx":-6.75,"yy":-79.85,"CASOS":5},{"ANIO":2025,"MES":2,"DPTO_HECHO":"LAMBAYEQUE","PROV_HECHO":"CHICLAYO","DIST_HECHO":"JOSE LEONARDO ORTIZ","ID_MODALIDAD":"01050101","MODALIDAD":"HURTO","xx":-6.75,"yy":-79.85,"CASOS":14},{"ANIO":2025,"MES":3,"DPTO_HECHO":"LAMBAYEQUE","PROV_HECHO":"CHICLAYO","DIST_HECHO":"CHICLAYO","ID_MODALIDAD":"05040202","MODALIDAD":"VIOLENCIA PSICOLOGICA","xx":-6.8,"yy":-79.85,"CASOS":7},{"ANIO":2025,"MES":9,"DPTO_HECHO":"LAMBAYEQUE","PROV_HECHO":"CHICLAYO","DIST_HECHO":"JOSE LEONARDO ORTIZ","ID_MODALIDAD":"01050215","MODALIDAD":"ROBO AGRAVADO","xx":-6.75,"yy":-79.85,"CASOS":15},{"ANIO":2025,"MES":7,"DPTO_HECHO":"LAMBAYEQUE","PROV_HECHO":"CHICLAYO","DIST_HECHO":"PATAPO","ID_MODALIDAD":"01120102","MODALIDAD":"CONDUCCION EN ESTADO DE EBRIEDAD O DROGADICCION","xx":-6.75,"yy":-79.65,"CASOS":5},{"ANIO":2025,"MES":7,"DPTO_HECHO":"LAMBAYEQUE","PROV_HECHO":"CHICLAYO","DIST_HECHO":"JOSE LEONARDO ORTIZ","ID_MODALIDAD":"01050101","MODALIDAD":"HURTO","xx":-6.75,"yy":-79.85,"CASOS":11},{"ANIO":2025,"MES":12,"DPTO_HECHO":"LAMBAYEQUE","PROV_HECHO":"CHICLAYO","DIST_HECHO":"LA VICTORIA","ID_MODALIDAD":"01050122","MODALIDAD":"HURTO DE CELULAR","xx":-6.8,"yy":-79.85,"CASOS":10},{"ANIO":2025,"MES":12,"DPTO_HECHO":"LAMBAYEQUE","PROV_HECHO":"LAMBAYEQUE","DIST_HECHO":"OLMOS","ID_MODALIDAD":"01050101","MODALIDAD":"HURTO","xx":-6.0,"yy":-79.75,"CASOS":5},{"ANIO":2025,"MES":9,"DPTO_HECHO":"LAMBAYEQUE","PROV_HECHO":"CHICLAYO","DIST_HECHO":"CHICLAYO","ID_MODALIDAD":"05080401","MODALIDAD":"FRAUDE INFORMATICO","xx":-6.75,"yy":-79.85,"CASOS":5},{"ANIO":2025,"MES":3,"DPTO_HECHO":"LAMBAYEQUE","PROV_HECHO":"CHICLAYO","DIST_HECHO":"PATAPO","ID_MODALIDAD":"01050101","MODALIDAD":"HURTO","xx":-6.75,"yy":-79.65,"CASOS":7},{"ANIO":2025,"MES":4,"DPTO_HECHO":"LAMBAYEQUE","PROV_HECHO":"LAMBAYEQUE","DIST_HECHO":"LAMBAYEQUE","ID_MODALIDAD":"01120102","MODALIDAD":"CONDUCCION EN ESTADO DE EBRIEDAD O DROGADICCION","xx":-6.7,"yy":-79.9,"CASOS":6},{"ANIO":2025,"MES":5,"DPTO_HECHO":"LAMBAYEQUE","PROV_HECHO":"CHICLAYO","DIST_HECHO":"JOSE LEONARDO ORTIZ","ID_MODALIDAD":"01050101","MODALIDAD":"HURTO","xx":-6.75,"yy":-79.85,"CASOS":12},{"ANIO":2025,"MES":4,"DPTO_HECHO":"LAMBAYEQUE","PROV_HECHO":"LAMBAYEQUE","DIST_HECHO":"LAMBAYEQUE","ID_MODALIDAD":"01050101","MODALIDAD":"HURTO","xx":-6.7,"yy":-79.9,"CASOS":9},{"ANIO":2025,"MES":6,"DPTO_HECHO":"LAMBAYEQUE","PROV_HECHO":"CHICLAYO","DIST_HECHO":"TUMAN","ID_MODALIDAD":"01120102","MODALIDAD":"CONDUCCION EN ESTADO DE EBRIEDAD O DROGADICCION","xx":-6.8,"yy":-79.7,"CASOS":5},{"ANIO":2025,"MES":6,"DPTO_HECHO":"LAMBAYEQUE","PROV_HECHO":"CHICLAYO","DIST_HECHO":"PATAPO","ID_MODALIDAD":"01300207","MODALIDAD":"AGRESION SIN DAÑO","xx":-6.75,"yy":-79.65,"CASOS":9},{"ANIO":2025,"MES":1,"DPTO_HECHO":"LAMBAYEQUE","PROV_HECHO":"CHICLAYO","DIST_HECHO":"CHICLAYO","ID_MODALIDAD":"05040202","MODALIDAD":"VIOLENCIA PSICOLOGICA","xx":-6.75,"yy":-79.85,"CASOS":10},{"ANIO":2025,"MES":12,"DPTO_HECHO":"LAMBAYEQUE","PROV_HECHO":"FERREÑAFE","DIST_HECHO":"FERREÑAFE","ID_MODALIDAD":"05040201","MODALIDAD":"VIOLENCIA FISICA","xx":-6.65,"yy":-79.8,"CASOS":11},{"ANIO":2025,"MES":11,"DPTO_HECHO":"LAMBAYEQUE","PROV_HECHO":"FERREÑAFE","DIST_HECHO":"FERREÑAFE","ID_MODALIDAD":"05040202","MODALIDAD":"VIOLENCIA PSICOLOGICA","xx":-6.65,"yy":-79.8,"CASOS":9},{"ANIO":2025,"MES":9,"DPTO_HECHO":"LAMBAYEQUE","PROV_HECHO":"LAMBAYEQUE","DIST_HECHO":"LAMBAYEQUE","ID_MODALIDAD":"01120117","MODALIDAD":"PRODUCCION DE PELIGRO EN EL SERVICIO PUBLICO DE TRANSPORTE DE PASAJEROS","xx":-6.7,"yy":-79.9,"CASOS":9},{"ANIO":2025,"MES":9,"DPTO_HECHO":"LAMBAYEQUE","PROV_HECHO":"CHICLAYO","DIST_HECHO":"JOSE LEONARDO ORTIZ","ID_MODALIDAD":"01050101","MODALIDAD":"HURTO","xx":-6.75,"yy":-79.85,"CASOS":14},{"ANIO":2025,"MES":12,"DPTO_HECHO":"LAMBAYEQUE","PROV_HECHO":"CHICLAYO","DIST_HECHO":"JOSE LEONARDO ORTIZ","ID_MODALIDAD":"05040201","MODALIDAD":"VIOLENCIA FISICA","xx":-6.75,"yy":-79.85,"CASOS":17},{"ANIO":2025,"MES":10,"DPTO_HECHO":"LAMBAYEQUE","PROV_HECHO":"CHICLAYO","DIST_HECHO":"CHICLAYO","ID_MODALIDAD":"01050107","MODALIDAD":"HURTO AGRAVADO","xx":-6.8,"yy":-79.85,"CASOS":8},{"ANIO":2025,"MES":11,"DPTO_HECHO":"LAMBAYEQUE","PROV_HECHO":"CHICLAYO","DIST_HECHO":"CHICLAYO","ID_MODALIDAD":"01050609","MODALIDAD":"ESTAFA AGRAVADA","xx":-6.75,"yy":-79.85,"CASOS":16},{"ANIO":2025,"MES":12,"DPTO_HECHO":"LAMBAYEQUE","PROV_HECHO":"CHICLAYO","DIST_HECHO":"CHICLAYO","ID_MODALIDAD":"05040201","MODALIDAD":"VIOLENCIA FISICA","xx":-6.75,"yy":-79.85,"CASOS":16},{"ANIO":2025,"MES":4,"DPTO_HECHO":"LAMBAYEQUE","PROV_HECHO":"CHICLAYO","DIST_HECHO":"JOSE LEONARDO ORTIZ","ID_MODALIDAD":"01050101","MODALIDAD":"HURTO","xx":-6.75,"yy":-79.85,"CASOS":14},{"ANIO":2025,"MES":5,"DPTO_HECHO":"LAMBAYEQUE","PROV_HECHO":"CHICLAYO","DIST_HECHO":"JOSE LEONARDO ORTIZ","ID_MODALIDAD":"05040201","MODALIDAD":"VIOLENCIA FISICA","xx":-6.75,"yy":-79.85,"CASOS":5},{"ANIO":2025,"MES":12,"DPTO_HECHO":"LAMBAYEQUE","PROV_HECHO":"CHICLAYO","DIST_HECHO":"JOSE LEONARDO ORTIZ","ID_MODALIDAD":"01050107","MODALIDAD":"HURTO AGRAVADO","xx":-6.75,"yy":-79.8,"CASOS":7},{"ANIO":2025,"MES":1,"DPTO_HECHO":"LAMBAYEQUE","PROV_HECHO":"FERREÑAFE","DIST_HECHO":"PUEBLO NUEVO","ID_MODALIDAD":"05040202","MODALIDAD":"VIOLENCIA PSICOLOGICA","xx":-6.65,"yy":-79.8,"CASOS":5},{"ANIO":2025,"MES":12,"DPTO_HECHO":"LAMBAYEQUE","PROV_HECHO":"CHICLAYO","DIST_HECHO":"LA VICTORIA","ID_MODALIDAD":"01050601","MODALIDAD":"ESTAFA","xx":-6.8,"yy":-79.85,"CASOS":7},{"ANIO":2025,"MES":3,"DPTO_HECHO":"LAMBAYEQUE","PROV_HECHO":"CHICLAYO","DIST_HECHO":"JOSE LEONARDO ORTIZ","ID_MODALIDAD":"05040202","MODALIDAD":"VIOLENCIA PSICOLOGICA","xx":-6.75,"yy":-79.85,"CASOS":10},{"ANIO":2025,"MES":7,"DPTO_HECHO":"LAMBAYEQUE","PROV_HECHO":"CHICLAYO","DIST_HECHO":"JOSE LEONARDO ORTIZ","ID_MODALIDAD":"01050107","MODALIDAD":"HURTO AGRAVADO","xx":-6.75,"yy":-79.85,"CASOS":13},{"ANIO":2025,"MES":2,"DPTO_HECHO":"LAMBAYEQUE","PROV_HECHO":"CHICLAYO","DIST_HECHO":"JOSE LEONARDO ORTIZ","ID_MODALIDAD":"05040202","MODALIDAD":"VIOLENCIA PSICOLOGICA","xx":-6.75,"yy":-79.85,"CASOS":9},{"ANIO":2025,"MES":3,"DPTO_HECHO":"LAMBAYEQUE","PROV_HECHO":"CHICLAYO","DIST_HECHO":"CHICLAYO","ID_MODALIDAD":"05040202","MODALIDAD":"VIOLENCIA PSICOLOGICA","xx":-6.75,"yy":-79.85,"CASOS":12},{"ANIO":2025,"MES":1,"DPTO_HECHO":"LAMBAYEQUE","PROV_HECHO":"FERREÑAFE","DIST_HECHO":"FERREÑAFE","ID_MODALIDAD":"05040202","MODALIDAD":"VIOLENCIA PSICOLOGICA","xx":-6.65,"yy":-79.8,"CASOS":11},{"ANIO":2025,"MES":10,"DPTO_HECHO":"LAMBAYEQUE","PROV_HECHO":"CHICLAYO","DIST_HECHO":"CHICLAYO","ID_MODALIDAD":"01120102","MODALIDAD":"CONDUCCION EN ESTADO DE EBRIEDAD O DROGADICCION","xx":-6.8,"yy":-79.85,"CASOS":7},{"ANIO":2025,"MES":2,"DPTO_HECHO":"LAMBAYEQUE","PROV_HECHO":"CHICLAYO","DIST_HECHO":"CHICLAYO","ID_MODALIDAD":"01050122","MODALIDAD":"HURTO DE CELULAR","xx":-6.75,"yy":-79.85,"CASOS":6},{"ANIO":2025,"MES":12,"DPTO_HECHO":"LAMBAYEQUE","PROV_HECHO":"LAMBAYEQUE","DIST_HECHO":"LAMBAYEQUE","ID_MODALIDAD":"05040202","MODALIDAD":"VIOLENCIA PSICOLOGICA","xx":-6.7,"yy":-79.9,"CASOS":6},{"ANIO":2025,"MES":7,"DPTO_HECHO":"LAMBAYEQUE","PROV_HECHO":"FERREÑAFE","DIST_HECHO":"FERREÑAFE","ID_MODALIDAD":"05040201","MODALIDAD":"VIOLENCIA FISICA","xx":-6.65,"yy":-79.8,"CASOS":7},{"ANIO":2025,"MES":4,"DPTO_HECHO":"LAMBAYEQUE","PROV_HECHO":"CHICLAYO","DIST_HECHO":"JOSE LEONARDO ORTIZ","ID_MODALIDAD":"01050215","MODALIDAD":"ROBO AGRAVADO","xx":-6.75,"yy":-79.85,"CASOS":9},{"ANIO":2025,"MES":7,"DPTO_HECHO":"LAMBAYEQUE","PROV_HECHO":"CHICLAYO","DIST_HECHO":"CHICLAYO","ID_MODALIDAD":"01050201","MODALIDAD":"ROBO","xx":-6.75,"yy":-79.85,"CASOS":8},{"ANIO":2025,"MES":4,"DPTO_HECHO":"LAMBAYEQUE","PROV_HECHO":"CHICLAYO","DIST_HECHO":"JOSE LEONARDO ORTIZ","ID_MODALIDAD":"01050501","MODALIDAD":"RECEPTACION","xx":-6.75,"yy":-79.85,"CASOS":12},{"ANIO":2025,"MES":12,"DPTO_HECHO":"LAMBAYEQUE","PROV_HECHO":"LAMBAYEQUE","DIST_HECHO":"TUCUME","ID_MODALIDAD":"01120102","MODALIDAD":"CONDUCCION EN ESTADO DE EBRIEDAD O DROGADICCION","xx":-6.5,"yy":-79.85,"CASOS":5},{"ANIO":2025,"MES":6,"DPTO_HECHO":"LAMBAYEQUE","PROV_HECHO":"FERREÑAFE","DIST_HECHO":"FERREÑAFE","ID_MODALIDAD":"05040202","MODALIDAD":"VIOLENCIA PSICOLOGICA","xx":-6.65,"yy":-79.8,"CASOS":10},{"ANIO":2025,"MES":12,"DPTO_HECHO":"LAMBAYEQUE","PROV_HECHO":"CHICLAYO","DIST_HECHO":"CAYALTI","ID_MODALIDAD":"01010316","MODALIDAD":"LESIONES","xx":-6.9,"yy":-79.55,"CASOS":5},{"ANIO":2025,"MES":12,"DPTO_HECHO":"LAMBAYEQUE","PROV_HECHO":"CHICLAYO","DIST_HECHO":"JOSE LEONARDO ORTIZ","ID_MODALIDAD":"01050119","MODALIDAD":"HURTO DE VEHICULO","xx":-6.75,"yy":-79.85,"CASOS":11},{"ANIO":2025,"MES":12,"DPTO_HECHO":"LAMBAYEQUE","PROV_HECHO":"CHICLAYO","DIST_HECHO":"CHICLAYO","ID_MODALIDAD":"01120102","MODALIDAD":"CONDUCCION EN ESTADO DE EBRIEDAD O DROGADICCION","xx":-6.75,"yy":-79.85,"CASOS":24},{"ANIO":2025,"MES":10,"DPTO_HECHO":"LAMBAYEQUE","PROV_HECHO":"LAMBAYEQUE","DIST_HECHO":"LAMBAYEQUE","ID_MODALIDAD":"01120117","MODALIDAD":"PRODUCCION DE PELIGRO EN EL SERVICIO PUBLICO DE TRANSPORTE DE PASAJEROS","xx":-6.7,"yy":-79.9,"CASOS":7},{"ANIO":2025,"MES":3,"DPTO_HECHO":"LAMBAYEQUE","PROV_HECHO":"CHICLAYO","DIST_HECHO":"JOSE LEONARDO ORTIZ","ID_MODALIDAD":"01050215","MODALIDAD":"ROBO AGRAVADO","xx":-6.75,"yy":-79.85,"CASOS":12},{"ANIO":2025,"MES":4,"DPTO_HECHO":"LAMBAYEQUE","PROV_HECHO":"CHICLAYO","DIST_HECHO":"JOSE LEONARDO ORTIZ","ID_MODALIDAD":"01050107","MODALIDAD":"HURTO AGRAVADO","xx":-6.75,"yy":-79.85,"CASOS":9},{"ANIO":2025,"MES":4,"DPTO_HECHO":"LAMBAYEQUE","PROV_HECHO":"CHICLAYO","DIST_HECHO":"POMALCA","ID_MODALIDAD":"01120102","MODALIDAD":"CONDUCCION EN ESTADO DE EBRIEDAD O DROGADICCION","xx":-6.75,"yy":-79.8,"CASOS":7},{"ANIO":2025,"MES":4,"DPTO_HECHO":"LAMBAYEQUE","PROV_HECHO":"CHICLAYO","DIST_HECHO":"CHICLAYO","ID_MODALIDAD":"01050215","MODALIDAD":"ROBO AGRAVADO","xx":-6.75,"yy":-79.85,"CASOS":5},{"ANIO":2025,"MES":4,"DPTO_HECHO":"LAMBAYEQUE","PROV_HECHO":"CHICLAYO","DIST_HECHO":"JOSE LEONARDO ORTIZ","ID_MODALIDAD":"05040201","MODALIDAD":"VIOLENCIA FISICA","xx":-6.75,"yy":-79.85,"CASOS":7},{"ANIO":2025,"MES":7,"DPTO_HECHO":"LAMBAYEQUE","PROV_HECHO":"CHICLAYO","DIST_HECHO":"CHICLAYO","ID_MODALIDAD":"01300201","MODALIDAD":"LESION DOLOSA","xx":-6.75,"yy":-79.85,"CASOS":7},{"ANIO":2025,"MES":12,"DPTO_HECHO":"LAMBAYEQUE","PROV_HECHO":"CHICLAYO","DIST_HECHO":"LA VICTORIA","ID_MODALIDAD":"01010316","MODALIDAD":"LESIONES","xx":-6.8,"yy":-79.85,"CASOS":9},{"ANIO":2025,"MES":10,"DPTO_HECHO":"LAMBAYEQUE","PROV_HECHO":"FERREÑAFE","DIST_HECHO":"FERREÑAFE","ID_MODALIDAD":"05040202","MODALIDAD":"VIOLENCIA PSICOLOGICA","xx":-6.65,"yy":-79.8,"CASOS":7},{"ANIO":2025,"MES":12,"DPTO_HECHO":"LAMBAYEQUE","PROV_HECHO":"CHICLAYO","DIST_HECHO":"CHICLAYO","ID_MODALIDAD":"01050201","MODALIDAD":"ROBO","xx":-6.75,"yy":-79.85,"CASOS":17},{"ANIO":2025,"MES":12,"DPTO_HECHO":"LAMBAYEQUE","PROV_HECHO":"FERREÑAFE","DIST_HECHO":"PUEBLO NUEVO","ID_MODALIDAD":"05040202","MODALIDAD":"VIOLENCIA PSICOLOGICA","xx":-6.65,"yy":-79.8,"CASOS":9},{"ANIO":2025,"MES":11,"DPTO_HECHO":"LAMBAYEQUE","PROV_HECHO":"CHICLAYO","DIST_HECHO":"CHICLAYO","ID_MODALIDAD":"01050107","MODALIDAD":"HURTO AGRAVADO","xx":-6.8,"yy":-79.85,"CASOS":10},{"ANIO":2025,"MES":9,"DPTO_HECHO":"LAMBAYEQUE","PROV_HECHO":"CHICLAYO","DIST_HECHO":"CHICLAYO","ID_MODALIDAD":"01040110","MODALIDAD":"ACOSO","xx":-6.75,"yy":-79.85,"CASOS":7},{"ANIO":2025,"MES":12,"DPTO_HECHO":"LAMBAYEQUE","PROV_HECHO":"CHICLAYO","DIST_HECHO":"CHICLAYO","ID_MODALIDAD":"05080401","MODALIDAD":"FRAUDE INFORMATICO","xx":-6.75,"yy":-79.85,"CASOS":12},{"ANIO":2025,"MES":8,"DPTO_HECHO":"LAMBAYEQUE","PROV_HECHO":"CHICLAYO","DIST_HECHO":"JOSE LEONARDO ORTIZ","ID_MODALIDAD":"05040202","MODALIDAD":"VIOLENCIA PSICOLOGICA","xx":-6.75,"yy":-79.85,"CASOS":8},{"ANIO":2025,"MES":8,"DPTO_HECHO":"LAMBAYEQUE","PROV_HECHO":"CHICLAYO","DIST_HECHO":"CHICLAYO","ID_MODALIDAD":"01050119","MODALIDAD":"HURTO DE VEHICULO","xx":-6.8,"yy":-79.85,"CASOS":14},{"ANIO":2025,"MES":2,"DPTO_HECHO":"LAMBAYEQUE","PROV_HECHO":"CHICLAYO","DIST_HECHO":"CHICLAYO","ID_MODALIDAD":"01050501","MODALIDAD":"RECEPTACION","xx":-6.75,"yy":-79.85,"CASOS":7},{"ANIO":2025,"MES":10,"DPTO_HECHO":"LAMBAYEQUE","PROV_HECHO":"CHICLAYO","DIST_HECHO":"CHICLAYO","ID_MODALIDAD":"01050601","MODALIDAD":"ESTAFA","xx":-6.75,"yy":-79.85,"CASOS":7},{"ANIO":2025,"MES":1,"DPTO_HECHO":"LAMBAYEQUE","PROV_HECHO":"CHICLAYO","DIST_HECHO":"JOSE LEONARDO ORTIZ","ID_MODALIDAD":"05040201","MODALIDAD":"VIOLENCIA FISICA","xx":-6.75,"yy":-79.85,"CASOS":5},{"ANIO":2025,"MES":9,"DPTO_HECHO":"LAMBAYEQUE","PROV_HECHO":"CHICLAYO","DIST_HECHO":"JOSE LEONARDO ORTIZ","ID_MODALIDAD":"05040201","MODALIDAD":"VIOLENCIA FISICA","xx":-6.75,"yy":-79.85,"CASOS":7},{"ANIO":2025,"MES":12,"DPTO_HECHO":"LAMBAYEQUE","PROV_HECHO":"CHICLAYO","DIST_HECHO":"PIMENTEL","ID_MODALIDAD":"01050215","MODALIDAD":"ROBO AGRAVADO","xx":-6.85,"yy":-79.95,"CASOS":5},{"ANIO":2025,"MES":11,"DPTO_HECHO":"LAMBAYEQUE","PROV_HECHO":"CHICLAYO","DIST_HECHO":"CHICLAYO","ID_MODALIDAD":"05080201","MODALIDAD":"ACCESO ILICITO ","xx":-6.75,"yy":-79.85,"CASOS":11},{"ANIO":2025,"MES":10,"DPTO_HECHO":"LAMBAYEQUE","PROV_HECHO":"CHICLAYO","DIST_HECHO":"JOSE LEONARDO ORTIZ","ID_MODALIDAD":"05040202","MODALIDAD":"VIOLENCIA PSICOLOGICA","xx":-6.75,"yy":-79.85,"CASOS":15},{"ANIO":2025,"MES":2,"DPTO_HECHO":"LAMBAYEQUE","PROV_HECHO":"CHICLAYO","DIST_HECHO":"POMALCA","ID_MODALIDAD":"01120102","MODALIDAD":"CONDUCCION EN ESTADO DE EBRIEDAD O DROGADICCION","xx":-6.75,"yy":-79.8,"CASOS":7},{"ANIO":2025,"MES":12,"DPTO_HECHO":"LAMBAYEQUE","PROV_HECHO":"CHICLAYO","DIST_HECHO":"CHICLAYO","ID_MODALIDAD":"01050121","MODALIDAD":"HURTO DE ACCESORIOS Y AUTOPARTES DE VEHICULOS","xx":-6.75,"yy":-79.85,"CASOS":5},{"ANIO":2025,"MES":8,"DPTO_HECHO":"LAMBAYEQUE","PROV_HECHO":"CHICLAYO","DIST_HECHO":"JOSE LEONARDO ORTIZ","ID_MODALIDAD":"05040201","MODALIDAD":"VIOLENCIA FISICA","xx":-6.75,"yy":-79.85,"CASOS":8},{"ANIO":2025,"MES":12,"DPTO_HECHO":"LAMBAYEQUE","PROV_HECHO":"CHICLAYO","DIST_HECHO":"CHICLAYO","ID_MODALIDAD":"01051001","MODALIDAD":"DAÑO SIMPLE","xx":-6.75,"yy":-79.85,"CASOS":5},{"ANIO":2025,"MES":5,"DPTO_HECHO":"LAMBAYEQUE","PROV_HECHO":"CHICLAYO","DIST_HECHO":"JOSE LEONARDO ORTIZ","ID_MODALIDAD":"01050215","MODALIDAD":"ROBO AGRAVADO","xx":-6.75,"yy":-79.85,"CASOS":10},{"ANIO":2025,"MES":11,"DPTO_HECHO":"LAMBAYEQUE","PROV_HECHO":"CHICLAYO","DIST_HECHO":"CHICLAYO","ID_MODALIDAD":"05080401","MODALIDAD":"FRAUDE INFORMATICO","xx":-6.8,"yy":-79.85,"CASOS":8},{"ANIO":2025,"MES":4,"DPTO_HECHO":"LAMBAYEQUE","PROV_HECHO":"CHICLAYO","DIST_HECHO":"CHICLAYO","ID_MODALIDAD":"05040202","MODALIDAD":"VIOLENCIA PSICOLOGICA","xx":-6.75,"yy":-79.85,"CASOS":8},{"ANIO":2025,"MES":12,"DPTO_HECHO":"LAMBAYEQUE","PROV_HECHO":"LAMBAYEQUE","DIST_HECHO":"LAMBAYEQUE","ID_MODALIDAD":"01050101","MODALIDAD":"HURTO","xx":-6.7,"yy":-79.9,"CASOS":8},{"ANIO":2025,"MES":12,"DPTO_HECHO":"LAMBAYEQUE","PROV_HECHO":"LAMBAYEQUE","DIST_HECHO":"OLMOS","ID_MODALIDAD":"05040201","MODALIDAD":"VIOLENCIA FISICA","xx":-6.0,"yy":-79.75,"CASOS":6},{"ANIO":2025,"MES":11,"DPTO_HECHO":"LAMBAYEQUE","PROV_HECHO":"CHICLAYO","DIST_HECHO":"JOSE LEONARDO ORTIZ","ID_MODALIDAD":"01050101","MODALIDAD":"HURTO","xx":-6.75,"yy":-79.85,"CASOS":16},{"ANIO":2025,"MES":4,"DPTO_HECHO":"LAMBAYEQUE","PROV_HECHO":"CHICLAYO","DIST_HECHO":"CHICLAYO","ID_MODALIDAD":"05040202","MODALIDAD":"VIOLENCIA PSICOLOGICA","xx":-6.8,"yy":-79.85,"CASOS":8},{"ANIO":2025,"MES":8,"DPTO_HECHO":"LAMBAYEQUE","PROV_HECHO":"CHICLAYO","DIST_HECHO":"JOSE LEONARDO ORTIZ","ID_MODALIDAD":"01050201","MODALIDAD":"ROBO","xx":-6.75,"yy":-79.85,"CASOS":5},{"ANIO":2025,"MES":3,"DPTO_HECHO":"LAMBAYEQUE","PROV_HECHO":"CHICLAYO","DIST_HECHO":"JOSE LEONARDO ORTIZ","ID_MODALIDAD":"01050101","MODALIDAD":"HURTO","xx":-6.75,"yy":-79.85,"CASOS":6},{"ANIO":2025,"MES":9,"DPTO_HECHO":"LAMBAYEQUE","PROV_HECHO":"CHICLAYO","DIST_HECHO":"CHICLAYO","ID_MODALIDAD":"01050119","MODALIDAD":"HURTO DE VEHICULO","xx":-6.8,"yy":-79.85,"CASOS":8},{"ANIO":2025,"MES":10,"DPTO_HECHO":"LAMBAYEQUE","PROV_HECHO":"CHICLAYO","DIST_HECHO":"CHICLAYO","ID_MODALIDAD":"01050119","MODALIDAD":"HURTO DE VEHICULO","xx":-6.8,"yy":-79.85,"CASOS":7},{"ANIO":2025,"MES":9,"DPTO_HECHO":"LAMBAYEQUE","PROV_HECHO":"CHICLAYO","DIST_HECHO":"CHICLAYO","ID_MODALIDAD":"01050201","MODALIDAD":"ROBO","xx":-6.75,"yy":-79.85,"CASOS":5},{"ANIO":2025,"MES":10,"DPTO_HECHO":"LAMBAYEQUE","PROV_HECHO":"CHICLAYO","DIST_HECHO":"JOSE LEONARDO ORTIZ","ID_MODALIDAD":"05040201","MODALIDAD":"VIOLENCIA FISICA","xx":-6.75,"yy":-79.85,"CASOS":12},{"ANIO":2025,"MES":12,"DPTO_HECHO":"LAMBAYEQUE","PROV_HECHO":"CHICLAYO","DIST_HECHO":"CHICLAYO","ID_MODALIDAD":"01300307","MODALIDAD":"HURTO SIMPLE ","xx":-6.8,"yy":-79.85,"CASOS":5},{"ANIO":2025,"MES":11,"DPTO_HECHO":"LAMBAYEQUE","PROV_HECHO":"CHICLAYO","DIST_HECHO":"JOSE LEONARDO ORTIZ","ID_MODALIDAD":"01300201","MODALIDAD":"LESION DOLOSA","xx":-6.75,"yy":-79.85,"CASOS":5},{"ANIO":2025,"MES":3,"DPTO_HECHO":"LAMBAYEQUE","PROV_HECHO":"FERREÑAFE","DIST_HECHO":"FERREÑAFE","ID_MODALIDAD":"05040201","MODALIDAD":"VIOLENCIA FISICA","xx":-6.65,"yy":-79.8,"CASOS":6},{"ANIO":2025,"MES":11,"DPTO_HECHO":"LAMBAYEQUE","PROV_HECHO":"CHICLAYO","DIST_HECHO":"CHICLAYO","ID_MODALIDAD":"01120102","MODALIDAD":"CONDUCCION EN ESTADO DE EBRIEDAD O DROGADICCION","xx":-6.8,"yy":-79.85,"CASOS":6},{"ANIO":2025,"MES":12,"DPTO_HECHO":"LAMBAYEQUE","PROV_HECHO":"LAMBAYEQUE","DIST_HECHO":"OLMOS","ID_MODALIDAD":"05040202","MODALIDAD":"VIOLENCIA PSICOLOGICA","xx":-6.0,"yy":-79.75,"CASOS":5},{"ANIO":2025,"MES":3,"DPTO_HECHO":"LAMBAYEQUE","PROV_HECHO":"CHICLAYO","DIST_HECHO":"JOSE LEONARDO ORTIZ","ID_MODALIDAD":"01050201","MODALIDAD":"ROBO","xx":-6.75,"yy":-79.85,"CASOS":7},{"ANIO":2025,"MES":10,"DPTO_HECHO":"LAMBAYEQUE","PROV_HECHO":"CHICLAYO","DIST_HECHO":"CHICLAYO","ID_MODALIDAD":"01050101","MODALIDAD":"HURTO","xx":-6.8,"yy":-79.85,"CASOS":5},{"ANIO":2025,"MES":2,"DPTO_HECHO":"LAMBAYEQUE","PROV_HECHO":"CHICLAYO","DIST_HECHO":"CHICLAYO","ID_MODALIDAD":"05040202","MODALIDAD":"VIOLENCIA PSICOLOGICA","xx":-6.8,"yy":-79.85,"CASOS":9},{"ANIO":2025,"MES":12,"DPTO_HECHO":"LAMBAYEQUE","PROV_HECHO":"CHICLAYO","DIST_HECHO":"LA VICTORIA","ID_MODALIDAD":"05040201","MODALIDAD":"VIOLENCIA FISICA","xx":-6.8,"yy":-79.85,"CASOS":7},{"ANIO":2025,"MES":11,"DPTO_HECHO":"LAMBAYEQUE","PROV_HECHO":"CHICLAYO","DIST_HECHO":"CHICLAYO","ID_MODALIDAD":"05040202","MODALIDAD":"VIOLENCIA PSICOLOGICA","xx":-6.75,"yy":-79.85,"CASOS":10},{"ANIO":2025,"MES":1,"DPTO_HECHO":"LAMBAYEQUE","PROV_HECHO":"CHICLAYO","DIST_HECHO":"JOSE LEONARDO ORTIZ","ID_MODALIDAD":"01050201","MODALIDAD":"ROBO","xx":-6.75,"yy":-79.85,"CASOS":9},{"ANIO":2025,"MES":12,"DPTO_HECHO":"LAMBAYEQUE","PROV_HECHO":"LAMBAYEQUE","DIST_HECHO":"LAMBAYEQUE","ID_MODALIDAD":"01010316","MODALIDAD":"LESIONES","xx":-6.7,"yy":-79.9,"CASOS":5},{"ANIO":2025,"MES":4,"DPTO_HECHO":"LAMBAYEQUE","PROV_HECHO":"CHICLAYO","DIST_HECHO":"JOSE LEONARDO ORTIZ","ID_MODALIDAD":"05040202","MODALIDAD":"VIOLENCIA PSICOLOGICA","xx":-6.75,"yy":-79.85,"CASOS":8},{"ANIO":2025,"MES":1,"DPTO_HECHO":"LAMBAYEQUE","PROV_HECHO":"CHICLAYO","DIST_HECHO":"CHICLAYO","ID_MODALIDAD":"01050101","MODALIDAD":"HURTO","xx":-6.8,"yy":-79.85,"CASOS":8},{"ANIO":2025,"MES":1,"DPTO_HECHO":"LAMBAYEQUE","PROV_HECHO":"CHICLAYO","DIST_HECHO":"JOSE LEONARDO ORTIZ","ID_MODALIDAD":"05040202","MODALIDAD":"VIOLENCIA PSICOLOGICA","xx":-6.75,"yy":-79.85,"CASOS":9},{"ANIO":2025,"MES":1,"DPTO_HECHO":"LAMBAYEQUE","PROV_HECHO":"FERREÑAFE","DIST_HECHO":"FERREÑAFE","ID_MODALIDAD":"05040201","MODALIDAD":"VIOLENCIA FISICA","xx":-6.65,"yy":-79.8,"CASOS":5},{"ANIO":2025,"MES":2,"DPTO_HECHO":"LAMBAYEQUE","PROV_HECHO":"CHICLAYO","DIST_HECHO":"JOSE LEONARDO ORTIZ","ID_MODALIDAD":"01050501","MODALIDAD":"RECEPTACION","xx":-6.75,"yy":-79.85,"CASOS":7},{"ANIO":2025,"MES":1,"DPTO_HECHO":"LAMBAYEQUE","PROV_HECHO":"CHICLAYO","DIST_HECHO":"CHICLAYO","ID_MODALIDAD":"01050201","MODALIDAD":"ROBO","xx":-6.8,"yy":-79.85,"CASOS":7},{"ANIO":2025,"MES":6,"DPTO_HECHO":"LAMBAYEQUE","PROV_HECHO":"CHICLAYO","DIST_HECHO":"JOSE LEONARDO ORTIZ","ID_MODALIDAD":"05040202","MODALIDAD":"VIOLENCIA PSICOLOGICA","xx":-6.75,"yy":-79.85,"CASOS":6},{"ANIO":2025,"MES":5,"DPTO_HECHO":"LAMBAYEQUE","PROV_HECHO":"FERREÑAFE","DIST_HECHO":"FERREÑAFE","ID_MODALIDAD":"05040201","MODALIDAD":"VIOLENCIA FISICA","xx":-6.65,"yy":-79.8,"CASOS":6},{"ANIO":2025,"MES":3,"DPTO_HECHO":"LAMBAYEQUE","PROV_HECHO":"FERREÑAFE","DIST_HECHO":"FERREÑAFE","ID_MODALIDAD":"05040202","MODALIDAD":"VIOLENCIA PSICOLOGICA","xx":-6.65,"yy":-79.8,"CASOS":10},{"ANIO":2025,"MES":5,"DPTO_HECHO":"LAMBAYEQUE","PROV_HECHO":"CHICLAYO","DIST_HECHO":"OYOTUN","ID_MODALIDAD":"01010316","MODALIDAD":"LESIONES","xx":-6.85,"yy":-79.3,"CASOS":5},{"ANIO":2025,"MES":12,"DPTO_HECHO":"LAMBAYEQUE","PROV_HECHO":"LAMBAYEQUE","DIST_HECHO":"LAMBAYEQUE","ID_MODALIDAD":"01050107","MODALIDAD":"HURTO AGRAVADO","xx":-6.7,"yy":-79.9,"CASOS":5},{"ANIO":2025,"MES":6,"DPTO_HECHO":"LAMBAYEQUE","PROV_HECHO":"CHICLAYO","DIST_HECHO":"CHICLAYO","ID_MODALIDAD":"01050201","MODALIDAD":"ROBO","xx":-6.8,"yy":-79.85,"CASOS":5},{"ANIO":2025,"MES":3,"DPTO_HECHO":"LAMBAYEQUE","PROV_HECHO":"CHICLAYO","DIST_HECHO":"CHICLAYO","ID_MODALIDAD":"05040201","MODALIDAD":"VIOLENCIA FISICA","xx":-6.75,"yy":-79.85,"CASOS":5},{"ANIO":2025,"MES":2,"DPTO_HECHO":"LAMBAYEQUE","PROV_HECHO":"CHICLAYO","DIST_HECHO":"LA VICTORIA","ID_MODALIDAD":"01120102","MODALIDAD":"CONDUCCION EN ESTADO DE EBRIEDAD O DROGADICCION","xx":-6.8,"yy":-79.85,"CASOS":7},{"ANIO":2025,"MES":11,"DPTO_HECHO":"LAMBAYEQUE","PROV_HECHO":"CHICLAYO","DIST_HECHO":"JOSE LEONARDO ORTIZ","ID_MODALIDAD":"01050215","MODALIDAD":"ROBO AGRAVADO","xx":-6.75,"yy":-79.85,"CASOS":8},{"ANIO":2025,"MES":5,"DPTO_HECHO":"LAMBAYEQUE","PROV_HECHO":"CHICLAYO","DIST_HECHO":"PATAPO","ID_MODALIDAD":"01300207","MODALIDAD":"AGRESION SIN DAÑO","xx":-6.75,"yy":-79.65,"CASOS":6},{"ANIO":2025,"MES":3,"DPTO_HECHO":"LAMBAYEQUE","PROV_HECHO":"CHICLAYO","DIST_HECHO":"CHICLAYO","ID_MODALIDAD":"01050215","MODALIDAD":"ROBO AGRAVADO","xx":-6.75,"yy":-79.85,"CASOS":9},{"ANIO":2025,"MES":12,"DPTO_HECHO":"LAMBAYEQUE","PROV_HECHO":"CHICLAYO","DIST_HECHO":"CHICLAYO","ID_MODALIDAD":"01050201","MODALIDAD":"ROBO","xx":-6.8,"yy":-79.85,"CASOS":6},{"ANIO":2025,"MES":7,"DPTO_HECHO":"LAMBAYEQUE","PROV_HECHO":"CHICLAYO","DIST_HECHO":"CHICLAYO","ID_MODALIDAD":"01050107","MODALIDAD":"HURTO AGRAVADO","xx":-6.8,"yy":-79.85,"CASOS":7},{"ANIO":2025,"MES":11,"DPTO_HECHO":"LAMBAYEQUE","PROV_HECHO":"CHICLAYO","DIST_HECHO":"JOSE LEONARDO ORTIZ","ID_MODALIDAD":"01050119","MODALIDAD":"HURTO DE VEHICULO","xx":-6.75,"yy":-79.85,"CASOS":7},{"ANIO":2025,"MES":3,"DPTO_HECHO":"LAMBAYEQUE","PROV_HECHO":"CHICLAYO","DIST_HECHO":"JOSE LEONARDO ORTIZ","ID_MODALIDAD":"01050501","MODALIDAD":"RECEPTACION","xx":-6.75,"yy":-79.85,"CASOS":14},{"ANIO":2025,"MES":8,"DPTO_HECHO":"LAMBAYEQUE","PROV_HECHO":"CHICLAYO","DIST_HECHO":"CHICLAYO","ID_MODALIDAD":"01050215","MODALIDAD":"ROBO AGRAVADO","xx":-6.75,"yy":-79.85,"CASOS":8},{"ANIO":2025,"MES":3,"DPTO_HECHO":"LAMBAYEQUE","PROV_HECHO":"CHICLAYO","DIST_HECHO":"PATAPO","ID_MODALIDAD":"01120102","MODALIDAD":"CONDUCCION EN ESTADO DE EBRIEDAD O DROGADICCION","xx":-6.75,"yy":-79.65,"CASOS":6},{"ANIO":2025,"MES":1,"DPTO_HECHO":"LAMBAYEQUE","PROV_HECHO":"FERREÑAFE","DIST_HECHO":"FERREÑAFE","ID_MODALIDAD":"01120102","MODALIDAD":"CONDUCCION EN ESTADO DE EBRIEDAD O DROGADICCION","xx":-6.65,"yy":-79.8,"CASOS":5},{"ANIO":2025,"MES":12,"DPTO_HECHO":"LAMBAYEQUE","PROV_HECHO":"FERREÑAFE","DIST_HECHO":"FERREÑAFE","ID_MODALIDAD":"01010316","MODALIDAD":"LESIONES","xx":-6.65,"yy":-79.8,"CASOS":6},{"ANIO":2025,"MES":12,"DPTO_HECHO":"LAMBAYEQUE","PROV_HECHO":"CHICLAYO","DIST_HECHO":"CHICLAYO","ID_MODALIDAD":"01120340","MODALIDAD":"TRAFICO ILICITO DE DROGAS","xx":-6.75,"yy":-79.85,"CASOS":8},{"ANIO":2025,"MES":11,"DPTO_HECHO":"LAMBAYEQUE","PROV_HECHO":"CHICLAYO","DIST_HECHO":"CHICLAYO","ID_MODALIDAD":"01050601","MODALIDAD":"ESTAFA","xx":-6.8,"yy":-79.85,"CASOS":8},{"ANIO":2025,"MES":10,"DPTO_HECHO":"LAMBAYEQUE","PROV_HECHO":"CHICLAYO","DIST_HECHO":"CHICLAYO","ID_MODALIDAD":"01050107","MODALIDAD":"HURTO AGRAVADO","xx":-6.75,"yy":-79.85,"CASOS":9},{"ANIO":2025,"MES":12,"DPTO_HECHO":"LAMBAYEQUE","PROV_HECHO":"CHICLAYO","DIST_HECHO":"JOSE LEONARDO ORTIZ","ID_MODALIDAD":"01300210","MODALIDAD":"MALTRATO","xx":-6.75,"yy":-79.85,"CASOS":6},{"ANIO":2025,"MES":2,"DPTO_HECHO":"LAMBAYEQUE","PROV_HECHO":"CHICLAYO","DIST_HECHO":"PATAPO","ID_MODALIDAD":"01120102","MODALIDAD":"CONDUCCION EN ESTADO DE EBRIEDAD O DROGADICCION","xx":-6.75,"yy":-79.65,"CASOS":6},{"ANIO":2025,"MES":7,"DPTO_HECHO":"LAMBAYEQUE","PROV_HECHO":"CHICLAYO","DIST_HECHO":"JOSE LEONARDO ORTIZ","ID_MODALIDAD":"05040201","MODALIDAD":"VIOLENCIA FISICA","xx":-6.75,"yy":-79.85,"CASOS":5},{"ANIO":2025,"MES":6,"DPTO_HECHO":"LAMBAYEQUE","PROV_HECHO":"CHICLAYO","DIST_HECHO":"PATAPO","ID_MODALIDAD":"01120102","MODALIDAD":"CONDUCCION EN ESTADO DE EBRIEDAD O DROGADICCION","xx":-6.75,"yy":-79.65,"CASOS":5},{"ANIO":2025,"MES":11,"DPTO_HECHO":"LAMBAYEQUE","PROV_HECHO":"CHICLAYO","DIST_HECHO":"PUCALA","ID_MODALIDAD":"01120102","MODALIDAD":"CONDUCCION EN ESTADO DE EBRIEDAD O DROGADICCION","xx":-6.8,"yy":-79.6,"CASOS":5},{"ANIO":2025,"MES":7,"DPTO_HECHO":"LAMBAYEQUE","PROV_HECHO":"CHICLAYO","DIST_HECHO":"CHICLAYO","ID_MODALIDAD":"01050119","MODALIDAD":"HURTO DE VEHICULO","xx":-6.8,"yy":-79.85,"CASOS":7},{"ANIO":2025,"MES":12,"DPTO_HECHO":"LAMBAYEQUE","PROV_HECHO":"CHICLAYO","DIST_HECHO":"CHICLAYO","ID_MODALIDAD":"05040201","MODALIDAD":"VIOLENCIA FISICA","xx":-6.8,"yy":-79.85,"CASOS":8},{"ANIO":2025,"MES":7,"DPTO_HECHO":"LAMBAYEQUE","PROV_HECHO":"CHICLAYO","DIST_HECHO":"OYOTUN","ID_MODALIDAD":"01120102","MODALIDAD":"CONDUCCION EN ESTADO DE EBRIEDAD O DROGADICCION","xx":-6.85,"yy":-79.3,"CASOS":5},{"ANIO":2025,"MES":4,"DPTO_HECHO":"LAMBAYEQUE","PROV_HECHO":"FERREÑAFE","DIST_HECHO":"FERREÑAFE","ID_MODALIDAD":"05040201","MODALIDAD":"VIOLENCIA FISICA","xx":-6.65,"yy":-79.8,"CASOS":6},{"ANIO":2025,"MES":2,"DPTO_HECHO":"LAMBAYEQUE","PROV_HECHO":"CHICLAYO","DIST_HECHO":"LA VICTORIA","ID_MODALIDAD":"05040202","MODALIDAD":"VIOLENCIA PSICOLOGICA","xx":-6.8,"yy":-79.85,"CASOS":8},{"ANIO":2025,"MES":11,"DPTO_HECHO":"LAMBAYEQUE","PROV_HECHO":"LAMBAYEQUE","DIST_HECHO":"MORROPE","ID_MODALIDAD":"01120102","MODALIDAD":"CONDUCCION EN ESTADO DE EBRIEDAD O DROGADICCION","xx":-6.5,"yy":-79.95,"CASOS":5},{"ANIO":2025,"MES":11,"DPTO_HECHO":"LAMBAYEQUE","PROV_HECHO":"CHICLAYO","DIST_HECHO":"JOSE LEONARDO ORTIZ","ID_MODALIDAD":"05040201","MODALIDAD":"VIOLENCIA FISICA","xx":-6.75,"yy":-79.85,"CASOS":8},{"ANIO":2025,"MES":12,"DPTO_HECHO":"LAMBAYEQUE","PROV_HECHO":"CHICLAYO","DIST_HECHO":"CHICLAYO","ID_MODALIDAD":"05040202","MODALIDAD":"VIOLENCIA PSICOLOGICA","xx":-6.8,"yy":-79.85,"CASOS":12},{"ANIO":2025,"MES":3,"DPTO_HECHO":"LAMBAYEQUE","PROV_HECHO":"CHICLAYO","DIST_HECHO":"CHICLAYO","ID_MODALIDAD":"01050201","MODALIDAD":"ROBO","xx":-6.8,"yy":-79.85,"CASOS":5},{"ANIO":2025,"MES":12,"DPTO_HECHO":"LAMBAYEQUE","PROV_HECHO":"CHICLAYO","DIST_HECHO":"CHICLAYO","ID_MODALIDAD":"05080401","MODALIDAD":"FRAUDE INFORMATICO","xx":-6.8,"yy":-79.85,"CASOS":10},{"ANIO":2025,"MES":4,"DPTO_HECHO":"LAMBAYEQUE","PROV_HECHO":"CHICLAYO","DIST_HECHO":"LA VICTORIA","ID_MODALIDAD":"05040202","MODALIDAD":"VIOLENCIA PSICOLOGICA","xx":-6.8,"yy":-79.85,"CASOS":6},{"ANIO":2025,"MES":9,"DPTO_HECHO":"LAMBAYEQUE","PROV_HECHO":"CHICLAYO","DIST_HECHO":"CHICLAYO","ID_MODALIDAD":"01050101","MODALIDAD":"HURTO","xx":-6.8,"yy":-79.85,"CASOS":7},{"ANIO":2025,"MES":12,"DPTO_HECHO":"LAMBAYEQUE","PROV_HECHO":"CHICLAYO","DIST_HECHO":"JOSE LEONARDO ORTIZ","ID_MODALIDAD":"01050215","MODALIDAD":"ROBO AGRAVADO","xx":-6.75,"yy":-79.85,"CASOS":6},{"ANIO":2025,"MES":9,"DPTO_HECHO":"LAMBAYEQUE","PROV_HECHO":"CHICLAYO","DIST_HECHO":"JOSE LEONARDO ORTIZ","ID_MODALIDAD":"01050122","MODALIDAD":"HURTO DE CELULAR","xx":-6.75,"yy":-79.85,"CASOS":7},{"ANIO":2025,"MES":7,"DPTO_HECHO":"LAMBAYEQUE","PROV_HECHO":"CHICLAYO","DIST_HECHO":"JOSE LEONARDO ORTIZ","ID_MODALIDAD":"01050119","MODALIDAD":"HURTO DE VEHICULO","xx":-6.75,"yy":-79.85,"CASOS":7},{"ANIO":2025,"MES":7,"DPTO_HECHO":"LAMBAYEQUE","PROV_HECHO":"CHICLAYO","DIST_HECHO":"CHICLAYO","ID_MODALIDAD":"01050601","MODALIDAD":"ESTAFA","xx":-6.75,"yy":-79.85,"CASOS":6},{"ANIO":2025,"MES":10,"DPTO_HECHO":"LAMBAYEQUE","PROV_HECHO":"CHICLAYO","DIST_HECHO":"JOSE LEONARDO ORTIZ","ID_MODALIDAD":"01050215","MODALIDAD":"ROBO AGRAVADO","xx":-6.75,"yy":-79.85,"CASOS":9},{"ANIO":2025,"MES":8,"DPTO_HECHO":"LAMBAYEQUE","PROV_HECHO":"CHICLAYO","DIST_HECHO":"JOSE LEONARDO ORTIZ","ID_MODALIDAD":"01050601","MODALIDAD":"ESTAFA","xx":-6.75,"yy":-79.85,"CASOS":5},{"ANIO":2025,"MES":11,"DPTO_HECHO":"LAMBAYEQUE","PROV_HECHO":"CHICLAYO","DIST_HECHO":"CHICLAYO","ID_MODALIDAD":"01010316","MODALIDAD":"LESIONES","xx":-6.8,"yy":-79.85,"CASOS":5},{"ANIO":2025,"MES":4,"DPTO_HECHO":"LAMBAYEQUE","PROV_HECHO":"CHICLAYO","DIST_HECHO":"PATAPO","ID_MODALIDAD":"01300207","MODALIDAD":"AGRESION SIN DAÑO","xx":-6.75,"yy":-79.65,"CASOS":5},{"ANIO":2025,"MES":12,"DPTO_HECHO":"LAMBAYEQUE","PROV_HECHO":"CHICLAYO","DIST_HECHO":"LA VICTORIA","ID_MODALIDAD":"01050107","MODALIDAD":"HURTO AGRAVADO","xx":-6.8,"yy":-79.85,"CASOS":8},{"ANIO":2025,"MES":4,"DPTO_HECHO":"LAMBAYEQUE","PROV_HECHO":"CHICLAYO","DIST_HECHO":"CHICLAYO","ID_MODALIDAD":"01300201","MODALIDAD":"LESION DOLOSA","xx":-6.8,"yy":-79.85,"CASOS":5},{"ANIO":2025,"MES":9,"DPTO_HECHO":"LAMBAYEQUE","PROV_HECHO":"CHICLAYO","DIST_HECHO":"CHICLAYO","ID_MODALIDAD":"01050204","MODALIDAD":"ROBO AGRAVADO A MANO ARMADA","xx":-6.8,"yy":-79.85,"CASOS":5},{"ANIO":2025,"MES":3,"DPTO_HECHO":"LAMBAYEQUE","PROV_HECHO":"CHICLAYO","DIST_HECHO":"JOSE LEONARDO ORTIZ","ID_MODALIDAD":"01050107","MODALIDAD":"HURTO AGRAVADO","xx":-6.75,"yy":-79.85,"CASOS":6},{"ANIO":2025,"MES":2,"DPTO_HECHO":"LAMBAYEQUE","PROV_HECHO":"CHICLAYO","DIST_HECHO":"CHICLAYO","ID_MODALIDAD":"01050215","MODALIDAD":"ROBO AGRAVADO","xx":-6.75,"yy":-79.85,"CASOS":9},{"ANIO":2025,"MES":9,"DPTO_HECHO":"LAMBAYEQUE","PROV_HECHO":"CHICLAYO","DIST_HECHO":"TUMAN","ID_MODALIDAD":"01120102","MODALIDAD":"CONDUCCION EN ESTADO DE EBRIEDAD O DROGADICCION","xx":-6.8,"yy":-79.7,"CASOS":5},{"ANIO":2025,"MES":1,"DPTO_HECHO":"LAMBAYEQUE","PROV_HECHO":"CHICLAYO","DIST_HECHO":"CHICLAYO","ID_MODALIDAD":"01050104","MODALIDAD":"HURTO AGRAVADO DURANTE LA NOCHE","xx":-6.75,"yy":-79.85,"CASOS":6},{"ANIO":2025,"MES":2,"DPTO_HECHO":"LAMBAYEQUE","PROV_HECHO":"CHICLAYO","DIST_HECHO":"CHICLAYO","ID_MODALIDAD":"01050107","MODALIDAD":"HURTO AGRAVADO","xx":-6.8,"yy":-79.85,"CASOS":8},{"ANIO":2025,"MES":4,"DPTO_HECHO":"LAMBAYEQUE","PROV_HECHO":"CHICLAYO","DIST_HECHO":"JOSE LEONARDO ORTIZ","ID_MODALIDAD":"01010316","MODALIDAD":"LESIONES","xx":-6.75,"yy":-79.85,"CASOS":8},{"ANIO":2025,"MES":3,"DPTO_HECHO":"LAMBAYEQUE","PROV_HECHO":"CHICLAYO","DIST_HECHO":"PATAPO","ID_MODALIDAD":"01010316","MODALIDAD":"LESIONES","xx":-6.75,"yy":-79.65,"CASOS":6},{"ANIO":2025,"MES":9,"DPTO_HECHO":"LAMBAYEQUE","PROV_HECHO":"FERREÑAFE","DIST_HECHO":"FERREÑAFE","ID_MODALIDAD":"05040202","MODALIDAD":"VIOLENCIA PSICOLOGICA","xx":-6.65,"yy":-79.8,"CASOS":5},{"ANIO":2025,"MES":8,"DPTO_HECHO":"LAMBAYEQUE","PROV_HECHO":"CHICLAYO","DIST_HECHO":"JOSE LEONARDO ORTIZ","ID_MODALIDAD":"01050215","MODALIDAD":"ROBO AGRAVADO","xx":-6.75,"yy":-79.85,"CASOS":11},{"ANIO":2025,"MES":5,"DPTO_HECHO":"LAMBAYEQUE","PROV_HECHO":"CHICLAYO","DIST_HECHO":"JOSE LEONARDO ORTIZ","ID_MODALIDAD":"05040202","MODALIDAD":"VIOLENCIA PSICOLOGICA","xx":-6.75,"yy":-79.85,"CASOS":7},{"ANIO":2025,"MES":12,"DPTO_HECHO":"LAMBAYEQUE","PROV_HECHO":"LAMBAYEQUE","DIST_HECHO":"LAMBAYEQUE","ID_MODALIDAD":"01050119","MODALIDAD":"HURTO DE VEHICULO","xx":-6.7,"yy":-79.9,"CASOS":7},{"ANIO":2025,"MES":9,"DPTO_HECHO":"LAMBAYEQUE","PROV_HECHO":"CHICLAYO","DIST_HECHO":"JOSE LEONARDO ORTIZ","ID_MODALIDAD":"01050501","MODALIDAD":"RECEPTACION","xx":-6.75,"yy":-79.85,"CASOS":6},{"ANIO":2025,"MES":9,"DPTO_HECHO":"LAMBAYEQUE","PROV_HECHO":"CHICLAYO","DIST_HECHO":"JOSE LEONARDO ORTIZ","ID_MODALIDAD":"01050119","MODALIDAD":"HURTO DE VEHICULO","xx":-6.75,"yy":-79.85,"CASOS":6},{"ANIO":2025,"MES":10,"DPTO_HECHO":"LAMBAYEQUE","PROV_HECHO":"CHICLAYO","DIST_HECHO":"LA VICTORIA","ID_MODALIDAD":"01120102","MODALIDAD":"CONDUCCION EN ESTADO DE EBRIEDAD O DROGADICCION","xx":-6.8,"yy":-79.85,"CASOS":6},{"ANIO":2025,"MES":8,"DPTO_HECHO":"LAMBAYEQUE","PROV_HECHO":"CHICLAYO","DIST_HECHO":"CHICLAYO","ID_MODALIDAD":"05040202","MODALIDAD":"VIOLENCIA PSICOLOGICA","xx":-6.8,"yy":-79.85,"CASOS":7},{"ANIO":2025,"MES":12,"DPTO_HECHO":"LAMBAYEQUE","PROV_HECHO":"CHICLAYO","DIST_HECHO":"CHICLAYO","ID_MODALIDAD":"01010316","MODALIDAD":"LESIONES","xx":-6.75,"yy":-79.85,"CASOS":8},{"ANIO":2025,"MES":9,"DPTO_HECHO":"LAMBAYEQUE","PROV_HECHO":"CHICLAYO","DIST_HECHO":"JOSE LEONARDO ORTIZ","ID_MODALIDAD":"01300201","MODALIDAD":"LESION DOLOSA","xx":-6.75,"yy":-79.85,"CASOS":5},{"ANIO":2025,"MES":12,"DPTO_HECHO":"LAMBAYEQUE","PROV_HECHO":"CHICLAYO","DIST_HECHO":"LA VICTORIA","ID_MODALIDAD":"01050215","MODALIDAD":"ROBO AGRAVADO","xx":-6.8,"yy":-79.85,"CASOS":7},{"ANIO":2025,"MES":5,"DPTO_HECHO":"LAMBAYEQUE","PROV_HECHO":"CHICLAYO","DIST_HECHO":"CHICLAYO","ID_MODALIDAD":"05040202","MODALIDAD":"VIOLENCIA PSICOLOGICA","xx":-6.8,"yy":-79.85,"CASOS":6},{"ANIO":2025,"MES":12,"DPTO_HECHO":"LAMBAYEQUE","PROV_HECHO":"CHICLAYO","DIST_HECHO":"CHICLAYO","ID_MODALIDAD":"05080501","MODALIDAD":"SUPLANTACION DE IDENTIDAD","xx":-6.8,"yy":-79.85,"CASOS":5},{"ANIO":2025,"MES":12,"DPTO_HECHO":"LAMBAYEQUE","PROV_HECHO":"CHICLAYO","DIST_HECHO":"JOSE LEONARDO ORTIZ","ID_MODALIDAD":"01300201","MODALIDAD":"LESION DOLOSA","xx":-6.75,"yy":-79.85,"CASOS":10},{"ANIO":2025,"MES":12,"DPTO_HECHO":"LAMBAYEQUE","PROV_HECHO":"CHICLAYO","DIST_HECHO":"CHICLAYO","ID_MODALIDAD":"05080501","MODALIDAD":"SUPLANTACION DE IDENTIDAD","xx":-6.75,"yy":-79.85,"CASOS":6},{"ANIO":2025,"MES":1,"DPTO_HECHO":"LAMBAYEQUE","PROV_HECHO":"CHICLAYO","DIST_HECHO":"CHICLAYO","ID_MODALIDAD":"01050215","MODALIDAD":"ROBO AGRAVADO","xx":-6.75,"yy":-79.85,"CASOS":6},{"ANIO":2025,"MES":5,"DPTO_HECHO":"LAMBAYEQUE","PROV_HECHO":"CHICLAYO","DIST_HECHO":"CHICLAYO","ID_MODALIDAD":"01050107","MODALIDAD":"HURTO AGRAVADO","xx":-6.8,"yy":-79.85,"CASOS":7},{"ANIO":2025,"MES":6,"DPTO_HECHO":"LAMBAYEQUE","PROV_HECHO":"CHICLAYO","DIST_HECHO":"CHICLAYO","ID_MODALIDAD":"05040202","MODALIDAD":"VIOLENCIA PSICOLOGICA","xx":-6.75,"yy":-79.85,"CASOS":6},{"ANIO":2025,"MES":1,"DPTO_HECHO":"LAMBAYEQUE","PROV_HECHO":"CHICLAYO","DIST_HECHO":"CHICLAYO","ID_MODALIDAD":"05040202","MODALIDAD":"VIOLENCIA PSICOLOGICA","xx":-6.8,"yy":-79.85,"CASOS":6},{"ANIO":2025,"MES":6,"DPTO_HECHO":"LAMBAYEQUE","PROV_HECHO":"CHICLAYO","DIST_HECHO":"PATAPO","ID_MODALIDAD":"01010316","MODALIDAD":"LESIONES","xx":-6.75,"yy":-79.65,"CASOS":6},{"ANIO":2025,"MES":2,"DPTO_HECHO":"LAMBAYEQUE","PROV_HECHO":"CHICLAYO","DIST_HECHO":"JOSE LEONARDO ORTIZ","ID_MODALIDAD":"01050201","MODALIDAD":"ROBO","xx":-6.75,"yy":-79.85,"CASOS":7},{"ANIO":2025,"MES":9,"DPTO_HECHO":"LAMBAYEQUE","PROV_HECHO":"CHICLAYO","DIST_HECHO":"CHICLAYO","ID_MODALIDAD":"01050215","MODALIDAD":"ROBO AGRAVADO","xx":-6.75,"yy":-79.85,"CASOS":5},{"ANIO":2025,"MES":11,"DPTO_HECHO":"LAMBAYEQUE","PROV_HECHO":"CHICLAYO","DIST_HECHO":"CHICLAYO","ID_MODALIDAD":"05080501","MODALIDAD":"SUPLANTACION DE IDENTIDAD","xx":-6.75,"yy":-79.85,"CASOS":6},{"ANIO":2025,"MES":9,"DPTO_HECHO":"LAMBAYEQUE","PROV_HECHO":"CHICLAYO","DIST_HECHO":"CHICLAYO","ID_MODALIDAD":"05040202","MODALIDAD":"VIOLENCIA PSICOLOGICA","xx":-6.75,"yy":-79.85,"CASOS":6},{"ANIO":2025,"MES":12,"DPTO_HECHO":"LAMBAYEQUE","PROV_HECHO":"CHICLAYO","DIST_HECHO":"CHICLAYO","ID_MODALIDAD":"01050121","MODALIDAD":"HURTO DE ACCESORIOS Y AUTOPARTES DE VEHICULOS","xx":-6.8,"yy":-79.85,"CASOS":6},{"ANIO":2025,"MES":9,"DPTO_HECHO":"LAMBAYEQUE","PROV_HECHO":"CHICLAYO","DIST_HECHO":"JOSE LEONARDO ORTIZ","ID_MODALIDAD":"05040202","MODALIDAD":"VIOLENCIA PSICOLOGICA","xx":-6.75,"yy":-79.85,"CASOS":8},{"ANIO":2025,"MES":11,"DPTO_HECHO":"LAMBAYEQUE","PROV_HECHO":"CHICLAYO","DIST_HECHO":"CHICLAYO","ID_MODALIDAD":"01050215","MODALIDAD":"ROBO AGRAVADO","xx":-6.75,"yy":-79.85,"CASOS":5},{"ANIO":2025,"MES":9,"DPTO_HECHO":"LAMBAYEQUE","PROV_HECHO":"CHICLAYO","DIST_HECHO":"CHICLAYO","ID_MODALIDAD":"01120102","MODALIDAD":"CONDUCCION EN ESTADO DE EBRIEDAD O DROGADICCION","xx":-6.75,"yy":-79.85,"CASOS":5},{"ANIO":2025,"MES":1,"DPTO_HECHO":"LAMBAYEQUE","PROV_HECHO":"CHICLAYO","DIST_HECHO":"LA VICTORIA","ID_MODALIDAD":"01120102","MODALIDAD":"CONDUCCION EN ESTADO DE EBRIEDAD O DROGADICCION","xx":-6.8,"yy":-79.85,"CASOS":5},{"ANIO":2025,"MES":11,"DPTO_HECHO":"LAMBAYEQUE","PROV_HECHO":"CHICLAYO","DIST_HECHO":"JOSE LEONARDO ORTIZ","ID_MODALIDAD":"01050601","MODALIDAD":"ESTAFA","xx":-6.75,"yy":-79.85,"CASOS":6},{"ANIO":2025,"MES":8,"DPTO_HECHO":"LAMBAYEQUE","PROV_HECHO":"CHICLAYO","DIST_HECHO":"CHICLAYO","ID_MODALIDAD":"01050121","MODALIDAD":"HURTO DE ACCESORIOS Y AUTOPARTES DE VEHICULOS","xx":-6.75,"yy":-79.85,"CASOS":5},{"ANIO":2025,"MES":12,"DPTO_HECHO":"LAMBAYEQUE","PROV_HECHO":"CHICLAYO","DIST_HECHO":"PIMENTEL","ID_MODALIDAD":"01050107","MODALIDAD":"HURTO AGRAVADO","xx":-6.8,"yy":-79.9,"CASOS":5},{"ANIO":2025,"MES":12,"DPTO_HECHO":"LAMBAYEQUE","PROV_HECHO":"CHICLAYO","DIST_HECHO":"CHICLAYO","ID_MODALIDAD":"01300210","MODALIDAD":"MALTRATO","xx":-6.75,"yy":-79.85,"CASOS":6},{"ANIO":2025,"MES":1,"DPTO_HECHO":"LAMBAYEQUE","PROV_HECHO":"CHICLAYO","DIST_HECHO":"CHICLAYO","ID_MODALIDAD":"01050201","MODALIDAD":"ROBO","xx":-6.75,"yy":-79.85,"CASOS":5},{"ANIO":2025,"MES":10,"DPTO_HECHO":"LAMBAYEQUE","PROV_HECHO":"CHICLAYO","DIST_HECHO":"JOSE LEONARDO ORTIZ","ID_MODALIDAD":"01120102","MODALIDAD":"CONDUCCION EN ESTADO DE EBRIEDAD O DROGADICCION","xx":-6.75,"yy":-79.85,"CASOS":6},{"ANIO":2025,"MES":7,"DPTO_HECHO":"LAMBAYEQUE","PROV_HECHO":"CHICLAYO","DIST_HECHO":"JOSE LEONARDO ORTIZ","ID_MODALIDAD":"01050201","MODALIDAD":"ROBO","xx":-6.75,"yy":-79.85,"CASOS":7},{"ANIO":2025,"MES":2,"DPTO_HECHO":"LAMBAYEQUE","PROV_HECHO":"CHICLAYO","DIST_HECHO":"CHICLAYO","ID_MODALIDAD":"01050201","MODALIDAD":"ROBO","xx":-6.8,"yy":-79.85,"CASOS":5},{"ANIO":2025,"MES":6,"DPTO_HECHO":"LAMBAYEQUE","PROV_HECHO":"CHICLAYO","DIST_HECHO":"JOSE LEONARDO ORTIZ","ID_MODALIDAD":"01050501","MODALIDAD":"RECEPTACION","xx":-6.75,"yy":-79.85,"CASOS":6},{"ANIO":2025,"MES":12,"DPTO_HECHO":"LAMBAYEQUE","PROV_HECHO":"CHICLAYO","DIST_HECHO":"JOSE LEONARDO ORTIZ","ID_MODALIDAD":"01010316","MODALIDAD":"LESIONES","xx":-6.75,"yy":-79.85,"CASOS":6},{"ANIO":2025,"MES":5,"DPTO_HECHO":"LAMBAYEQUE","PROV_HECHO":"CHICLAYO","DIST_HECHO":"CHICLAYO","ID_MODALIDAD":"05040202","MODALIDAD":"VIOLENCIA PSICOLOGICA","xx":-6.75,"yy":-79.85,"CASOS":6},{"ANIO":2025,"MES":12,"DPTO_HECHO":"LAMBAYEQUE","PROV_HECHO":"CHICLAYO","DIST_HECHO":"CHICLAYO","ID_MODALIDAD":"01120102","MODALIDAD":"CONDUCCION EN ESTADO DE EBRIEDAD O DROGADICCION","xx":-6.8,"yy":-79.85,"CASOS":5},{"ANIO":2025,"MES":4,"DPTO_HECHO":"LAMBAYEQUE","PROV_HECHO":"FERREÑAFE","DIST_HECHO":"FERREÑAFE","ID_MODALIDAD":"05040202","MODALIDAD":"VIOLENCIA PSICOLOGICA","xx":-6.65,"yy":-79.8,"CASOS":5},{"ANIO":2025,"MES":1,"DPTO_HECHO":"LAMBAYEQUE","PROV_HECHO":"CHICLAYO","DIST_HECHO":"CHICLAYO","ID_MODALIDAD":"05040201","MODALIDAD":"VIOLENCIA FISICA","xx":-6.75,"yy":-79.85,"CASOS":6},{"ANIO":2025,"MES":7,"DPTO_HECHO":"LAMBAYEQUE","PROV_HECHO":"CHICLAYO","DIST_HECHO":"CHICLAYO","ID_MODALIDAD":"01050121","MODALIDAD":"HURTO DE ACCESORIOS Y AUTOPARTES DE VEHICULOS","xx":-6.75,"yy":-79.85,"CASOS":5},{"ANIO":2025,"MES":7,"DPTO_HECHO":"LAMBAYEQUE","PROV_HECHO":"CHICLAYO","DIST_HECHO":"JOSE LEONARDO ORTIZ","ID_MODALIDAD":"01300201","MODALIDAD":"LESION DOLOSA","xx":-6.75,"yy":-79.85,"CASOS":5},{"ANIO":2025,"MES":5,"DPTO_HECHO":"LAMBAYEQUE","PROV_HECHO":"LAMBAYEQUE","DIST_HECHO":"LAMBAYEQUE","ID_MODALIDAD":"01050101","MODALIDAD":"HURTO","xx":-6.7,"yy":-79.9,"CASOS":6},{"ANIO":2025,"MES":7,"DPTO_HECHO":"LAMBAYEQUE","PROV_HECHO":"FERREÑAFE","DIST_HECHO":"FERREÑAFE","ID_MODALIDAD":"01120102","MODALIDAD":"CONDUCCION EN ESTADO DE EBRIEDAD O DROGADICCION","xx":-6.65,"yy":-79.8,"CASOS":5},{"ANIO":2025,"MES":6,"DPTO_HECHO":"LAMBAYEQUE","PROV_HECHO":"CHICLAYO","DIST_HECHO":"CHICLAYO","ID_MODALIDAD":"01050403","MODALIDAD":"APROPIACION IRREGULAR","xx":-6.75,"yy":-79.85,"CASOS":5},{"ANIO":2025,"MES":12,"DPTO_HECHO":"LAMBAYEQUE","PROV_HECHO":"LAMBAYEQUE","DIST_HECHO":"LAMBAYEQUE","ID_MODALIDAD":"05040201","MODALIDAD":"VIOLENCIA FISICA","xx":-6.7,"yy":-79.9,"CASOS":5},{"ANIO":2025,"MES":3,"DPTO_HECHO":"LAMBAYEQUE","PROV_HECHO":"CHICLAYO","DIST_HECHO":"CHICLAYO","ID_MODALIDAD":"01050215","MODALIDAD":"ROBO AGRAVADO","xx":-6.8,"yy":-79.85,"CASOS":5},{"ANIO":2025,"MES":7,"DPTO_HECHO":"LAMBAYEQUE","PROV_HECHO":"CHICLAYO","DIST_HECHO":"CHICLAYO","ID_MODALIDAD":"05040201","MODALIDAD":"VIOLENCIA FISICA","xx":-6.75,"yy":-79.85,"CASOS":5},{"ANIO":2025,"MES":12,"DPTO_HECHO":"LAMBAYEQUE","PROV_HECHO":"CHICLAYO","DIST_HECHO":"JOSE LEONARDO ORTIZ","ID_MODALIDAD":"01050201","MODALIDAD":"ROBO","xx":-6.75,"yy":-79.85,"CASOS":5},{"ANIO":2025,"MES":11,"DPTO_HECHO":"LAMBAYEQUE","PROV_HECHO":"CHICLAYO","DIST_HECHO":"CHICLAYO","ID_MODALIDAD":"01050803","MODALIDAD":"EXTORSION","xx":-6.75,"yy":-79.85,"CASOS":7},{"ANIO":2025,"MES":12,"DPTO_HECHO":"LAMBAYEQUE","PROV_HECHO":"CHICLAYO","DIST_HECHO":"CHICLAYO","ID_MODALIDAD":"01050601","MODALIDAD":"ESTAFA","xx":-6.8,"yy":-79.85,"CASOS":5},{"ANIO":2025,"MES":6,"DPTO_HECHO":"LAMBAYEQUE","PROV_HECHO":"CHICLAYO","DIST_HECHO":"CHICLAYO","ID_MODALIDAD":"01050215","MODALIDAD":"ROBO AGRAVADO","xx":-6.75,"yy":-79.85,"CASOS":5},{"ANIO":2025,"MES":7,"DPTO_HECHO":"LAMBAYEQUE","PROV_HECHO":"CHICLAYO","DIST_HECHO":"JOSE LEONARDO ORTIZ","ID_MODALIDAD":"01050215","MODALIDAD":"ROBO AGRAVADO","xx":-6.75,"yy":-79.85,"CASOS":5}]