[{"ANIO":2025,"MES":8,"DPTO_HECHO":"PASCO","PROV_HECHO":"PASCO","DIST_HECHO":"YANACANCHA","ID_MODALIDAD":"01010316","MODALIDAD":"LESIONES","xx":-10.65,"yy":-76.25,"CASOS":8},{"ANIO":2025,"MES":5,"DPTO_HECHO":"PASCO","PROV_HECHO":"PASCO","DIST_HECHO":"CHAUPIMARCA","ID_MODALIDAD":"01050101","MODALIDAD":"HURTO","xx":-10.7,"yy":-76.25,"CASOS":9},{"ANIO":2025,"MES":5,"DPTO_HECHO":"PASCO","PROV_HECHO":"PASCO","DIST_HECHO":"PAUCARTAMBO","ID_MODALIDAD":"01120102","MODALIDAD":"CONDUCCION EN ESTADO DE EBRIEDAD O DROGADICCION","xx":-10.75,"yy":-75.8,"CASOS":5},{"ANIO":2025,"MES":12,"DPTO_HECHO":"PASCO","PROV_HECHO":"OXAPAMPA","DIST_HECHO":"OXAPAMPA","ID_MODALIDAD":"05040202","MODALIDAD":"VIOLENCIA PSICOLOGICA","xx":-10.6,"yy":-75.4,"CASOS":6},{"ANIO":2025,"MES":12,"DPTO_HECHO":"PASCO","PROV_HECHO":"OXAPAMPA","DIST_HECHO":"PUERTO BERMUDEZ","ID_MODALIDAD":"05040202","MODALIDAD":"VIOLENCIA PSICOLOGICA","xx":-10.3,"yy":-74.95,"CASOS":5},{"ANIO":2025,"MES":4,"DPTO_HECHO":"PASCO","PROV_HECHO":"PASCO","DIST_HECHO":"CHAUPIMARCA","ID_MODALIDAD":"01010316","MODALIDAD":"LESIONES","xx":-10.7,"yy":-76.25,"CASOS":6},{"ANIO":2025,"MES":11,"DPTO_HECHO":"PASCO","PROV_HECHO":"PASCO","DIST_HECHO":"CHAUPIMARCA","ID_MODALIDAD":"01010316","MODALIDAD":"LESIONES","xx":-10.7,"yy":-76.25,"CASOS":5},{"ANIO":2025,"MES":11,"DPTO_HECHO":"PASCO","PROV_HECHO":"PASCO","DIST_HECHO":"CHAUPIMARCA","ID_MODALIDAD":"01120102","MODALIDAD":"CONDUCCION EN ESTADO DE EBRIEDAD O DROGADICCION","xx":-10.7,"yy":-76.25,"CASOS":7},{"ANIO":2025,"MES":5,"DPTO_HECHO":"PASCO","PROV_HECHO":"PASCO","DIST_HECHO":"YANACANCHA","ID_MODALIDAD":"01120102","MODALIDAD":"CONDUCCION EN ESTADO DE EBRIEDAD O DROGADICCION","xx":-10.65,"yy":-76.25,"CASOS":5},{"ANIO":2025,"MES":12,"DPTO_HECHO":"PASCO","PROV_HECHO":"PASCO","DIST_HECHO":"YANACANCHA","ID_MODALIDAD":"01120102","MODALIDAD":"CONDUCCION EN ESTADO DE EBRIEDAD O DROGADICCION","xx":-10.65,"yy":-76.25,"CASOS":5}]